Workbook

Sheet P&L
A1: BUSINESS PLAN UMATCH - P&L (REGIME DE COMPETÊNCIA)
A3: Categoria | B3: Unidade | C3: 05/2024 | D3: 06/2024 | E3: 07/2024 | F3: 08/2024 | G3: 09/2024 | H3: 10/2024 | I3: 11/2024 | J3: 12/2024 | K3: 01/2025 | L3: 02/2025 | M3: 03/2025 | N3: 04/2025 | O3: 05/2025 | P3: 06/2025 | Q3: 07/2025 | R3: 08/2025 | S3: 09/2025 | T3: 10/2025
A5: NAU | B5: Users
A6: Brazil | B6: Users
A7: EaM | B7: Users
A8: Affiliates & Events | B8: Users
A9: Ads | B9: Users
A10: Organic | B10: Users
A11: USA | B11: Users
A12: EaM | B12: Users
A13: Ads | B13: Users
A14: Organic | B14: Users
A16: CPA | B16: BRL
A17: Brazil | B17: BRL
... A22: Ads | B22: BRL
A24: Revenue | B24: BRL | C24: =C25+C42 | D24: =D25+D42 | E24: =E25+E42 | F24: =F25+F42 | G24: =G25+G42 | H24: =H25+H42 | I24: =I25+I42 | J24: =J25+J42 | ... T24: =T25+T42
A25: Revenue no Tax (total das receitas recebidas em conta) | B25: BRL | C25: =C29+C37 | D25: =D29+D37 | E25: =E29+E37 | F25: =F29+F37 | G25: =G29+G37 | H25: =H29+H37 | I25: =I29+I37 | J25: =J29+J37 | ... T25: =T29+T37
A26: Google (IAPHUB) | B26: BRL | C26: 0 | D26: 0 | E26: 0 | F26: 0 | G26: 0 | H26: 0 | I26: 0 | J26: 0 | K26: 0 | L26: 0 | M26: 0 | N26: 0 | O26: 0 | P26: 0 | Q26: 0 | R26: 0 | S26: 0 | T26: 0
A27: Google (IAPHUB) x 0.85 | B27: BRL | C27: =C26*0.85 | D27: =D26*0.85 | E27: =E26*0.85 | F27: =F26*0.85 | G27: =G26*0.85 | H27: =H26*0.85 | I27: =I26*0.85 | J27: =J26*0.85 | ... T27: =T26*0.85
A28: Δ(%) | B28: % | C28: 0 | D28: =IFERROR((D27-C27)/C27,0) | E28: =IFERROR((E27-D27)/D27,0) | F28: =IFERROR((F27-E27)/E27,0) | G28: =IFERROR((G27-F27)/F27,0) | H28: =IFERROR((H27-G27)/G27,0) | I28: =IFERROR((I27-H27)/H27,0) | J28: =IFERROR((J27-I27)/I27,0) | K28: =IFERROR((K27-J27)/J27,0) | ... T28: =IFERROR((T27-S27)/S27,0)
A29: Google | B29: BRL | C29: =SUMIFS(Extrato_Importado!$E:$E,Extrato_Importado!$H:$H,"2024-05",Extrato_Importado!$B:$B,"Google Play Net Revenue") | D29: =SUMIFS(Extrato_Importado!$E:$E,Extrato_Importado!$H:$H,"2024-06",Extrato_Importado!$B:$B,"Google Play Net Revenue") | E29: =SUMIFS(Extrato_Importado!$E:$E,Extrato_Importado!$H:$H,"2024-07",Extrato_Importado!$B:$B,"Google Play Net Revenue") | F29: =SUMIFS(Extrato_Importado!$E:$E,Extrato_Importado!$H:$H,"2024-08",Extrato_Importado!$B:$B,"Google Play Net Revenue") | G29: =SUMIFS(Extrato_Importado!$E:$E,Extrato_Importado!$H:$H,"2024-09",Extrato_Importado!$B:$B,"Google Play Net Revenue") | H29: =SUMIFS(Extrato_Importado!$E:$E,Extrato_Importado!$H:$H,"2024-10",Extrato_Importado!$B:$B,"Google Play Net Revenue") | I29: =SUMIFS(Extrato_Importado!$E:$E,Extrato_Importado!$H:$H,"2024-11",Extrato_Importado!$B:$B,"Google Play Net Revenue") | J29: =SUMIFS(Extrato_Importado!$E:$E,Extrato_Importado!$H:$H,"2024-12",Extrato_Importado!$B:$B,"Google Play Net Revenue") | K29: =SUMIFS(Extrato_Importado!$E:$E,Extrato_Importado!$H:$H,"2025-01",Extrato_Importado!$B:$B,"Google Play Net Revenue") | L29: =SUMIFS(Extrato_Importado!$E:$E,Extrato_Importado!$H:$H,"2025-02",Extrato_Importado!$B:$B,"Google Play Net Revenue") | M29: =SUMIFS(Extrato_Importado!$E:$E,Extrato_Importado!$H:$H,"2025-03",Extrato_Importado!$B:$B,"Google Play Net Revenue") | N29: =SUMIFS(Extrato_Importado!$E:$E,Extrato_Importado!$H:$H,"2025-04",Extrato_Importado!$B:$B,"Google Play Net Revenue") | O29: =SUMIFS(Extrato_Importado!$E:$E,Extrato_Importado!$H:$H,"2025-05",Extrato_Importado!$B:$B,"Google Play Net Revenue") | P29: =SUMIFS(Extrato_Importado!$E:$E,Extrato_Importado!$H:$H,"2025-06",Extrato_Importado!$B:$B,"Google Play Net Revenue") | Q29: =SUMIFS(Extrato_Importado!$E:$E,Extrato_Importado!$H:$H,"2025-07",Extrato_Importado!$B:$B,"Google Play Net Revenue") | R29: =SUMIFS(Extrato_Importado!$E:$E,Extrato_Importado!$H:$H,"2025-08",Extrato_Importado!$B:$B,"Google Play Net Revenue") | S29: =SUMIFS(Extrato_Importado!$E:$E,Extrato_Importado!$H:$H,"2025-09",Extrato_Importado!$B:$B,"Google Play Net Revenue") | T29: =SUMIFS(Extrato_Importado!$E:$E,Extrato_Importado!$H:$H,"2025-10",Extrato_Importado!$B:$B,"Google Play Net Revenue")
A30: Brazil | B30: BRL | C30: =SUMIFS(Extrato_Importado!$E:$E,Extrato_Importado!$H:$H,"2024-05",Extrato_Importado!$B:$B,"Google Play Net Revenue") | D30: =SUMIFS(Extrato_Importado!$E:$E,Extrato_Importado!$H:$H,"2024-06",Extrato_Importado!$B:$B,"Google Play Net Revenue") | E30: =SUMIFS(Extrato_Importado!$E:$E,Extrato_Importado!$H:$H,"2024-07",Extrato_Importado!$B:$B,"Google Play Net Revenue") | F30: =SUMIFS(Extrato_Importado!$E:$E,Extrato_Importado!$H:$H,"2024-08",Extrato_Importado!$B:$B,"Google Play Net Revenue") | G30: =SUMIFS(Extrato_Importado!$E:$E,Extrato_Importado!$H:$H,"2024-09",Extrato_Importado!$B:$B,"Google Play Net Revenue") | H30: =SUMIFS(Extrato_Importado!$E:$E,Extrato_Importado!$H:$H,"2024-10",Extrato_Importado!$B:$B,"Google Play Net Revenue") | I30: =SUMIFS(Extrato_Importado!$E:$E,Extrato_Importado!$H:$H,"2024-11",Extrato_Importado!$B:$B,"Google Play Net Revenue") | J30: =SUMIFS(Extrato_Importado!$E:$E,Extrato_Importado!$H:$H,"2024-12",Extrato_Importado!$B:$B,"Google Play Net Revenue") | K30: =SUMIFS(Extrato_Importado!$E:$E,Extrato_Importado!$H:$H,"2025-01",Extrato_Importado!$B:$B,"Google Play Net Revenue") | L30: =SUMIFS(Extrato_Importado!$E:$E,Extrato_Importado!$H:$H,"2025-02",Extrato_Importado!$B:$B,"Google Play Net Revenue") | M30: =SUMIFS(Extrato_Importado!$E:$E,Extrato_Importado!$H:$H,"2025-03",Extrato_Importado!$B:$B,"Google Play Net Revenue") | N30: =SUMIFS(Extrato_Importado!$E:$E,Extrato_Importado!$H:$H,"2025-04",Extrato_Importado!$B:$B,"Google Play Net Revenue") | O30: =SUMIFS(Extrato_Importado!$E:$E,Extrato_Importado!$H:$H,"2025-05",Extrato_Importado!$B:$B,"Google Play Net Revenue") | P30: =SUMIFS(Extrato_Importado!$E:$E,Extrato_Importado!$H:$H,"2025-06",Extrato_Importado!$B:$B,"Google Play Net Revenue") | Q30: =SUMIFS(Extrato_Importado!$E:$E,Extrato_Importado!$H:$H,"2025-07",Extrato_Importado!$B:$B,"Google Play Net Revenue") | R30: =SUMIFS(Extrato_Importado!$E:$E,Extrato_Importado!$H:$H,"2025-08",Extrato_Importado!$B:$B,"Google Play Net Revenue") | S30: =SUMIFS(Extrato_Importado!$E:$E,Extrato_Importado!$H:$H,"2025-09",Extrato_Importado!$B:$B,"Google Play Net Revenue") | T30: =SUMIFS(Extrato_Importado!$E:$E,Extrato_Importado!$H:$H,"2025-10",Extrato_Importado!$B:$B,"Google Play Net Revenue")
A31: Brazil Margin (%) | B31: % | C31: =IFERROR(C30/C29,0) | D31: =IFERROR(D30/D29,0) | E31: =IFERROR(E30/E29,0) | F31: =IFERROR(F30/F29,0) | G31: =IFERROR(G30/G29,0) | H31: =IFERROR(H30/H29,0) | I31: =IFERROR(I30/I29,0) | J31: =IFERROR(J30/J29,0) | ... T31: =IFERROR(T30/T29,0)
A32: USA | B32: BRL | C32: =SUMIFS(Extrato_Importado!$E:$E,Extrato_Importado!$H:$H,"2024-05",Extrato_Importado!$B:$B,"Google Play Net Revenue") | D32: =SUMIFS(Extrato_Importado!$E:$E,Extrato_Importado!$H:$H,"2024-06",Extrato_Importado!$B:$B,"Google Play Net Revenue") | E32: =SUMIFS(Extrato_Importado!$E:$E,Extrato_Importado!$H:$H,"2024-07",Extrato_Importado!$B:$B,"Google Play Net Revenue") | F32: =SUMIFS(Extrato_Importado!$E:$E,Extrato_Importado!$H:$H,"2024-08",Extrato_Importado!$B:$B,"Google Play Net Revenue") | G32: =SUMIFS(Extrato_Importado!$E:$E,Extrato_Importado!$H:$H,"2024-09",Extrato_Importado!$B:$B,"Google Play Net Revenue") | H32: =SUMIFS(Extrato_Importado!$E:$E,Extrato_Importado!$H:$H,"2024-10",Extrato_Importado!$B:$B,"Google Play Net Revenue") | I32: =SUMIFS(Extrato_Importado!$E:$E,Extrato_Importado!$H:$H,"2024-11",Extrato_Importado!$B:$B,"Google Play Net Revenue") | J32: =SUMIFS(Extrato_Importado!$E:$E,Extrato_Importado!$H:$H,"2024-12",Extrato_Importado!$B:$B,"Google Play Net Revenue") | K32: =SUMIFS(Extrato_Importado!$E:$E,Extrato_Importado!$H:$H,"2025-01",Extrato_Importado!$B:$B,"Google Play Net Revenue") | L32: =SUMIFS(Extrato_Importado!$E:$E,Extrato_Importado!$H:$H,"2025-02",Extrato_Importado!$B:$B,"Google Play Net Revenue") | M32: =SUMIFS(Extrato_Importado!$E:$E,Extrato_Importado!$H:$H,"2025-03",Extrato_Importado!$B:$B,"Google Play Net Revenue") | N32: =SUMIFS(Extrato_Importado!$E:$E,Extrato_Importado!$H:$H,"2025-04",Extrato_Importado!$B:$B,"Google Play Net Revenue") | O32: =SUMIFS(Extrato_Importado!$E:$E,Extrato_Importado!$H:$H,"2025-05",Extrato_Importado!$B:$B,"Google Play Net Revenue") | P32: =SUMIFS(Extrato_Importado!$E:$E,Extrato_Importado!$H:$H,"2025-06",Extrato_Importado!$B:$B,"Google Play Net Revenue") | Q32: =SUMIFS(Extrato_Importado!$E:$E,Extrato_Importado!$H:$H,"2025-07",Extrato_Importado!$B:$B,"Google Play Net Revenue") | R32: =SUMIFS(Extrato_Importado!$E:$E,Extrato_Importado!$H:$H,"2025-08",Extrato_Importado!$B:$B,"Google Play Net Revenue") | S32: =SUMIFS(Extrato_Importado!$E:$E,Extrato_Importado!$H:$H,"2025-09",Extrato_Importado!$B:$B,"Google Play Net Revenue") | T32: =SUMIFS(Extrato_Importado!$E:$E,Extrato_Importado!$H:$H,"2025-10",Extrato_Importado!$B:$B,"Google Play Net Revenue")
A33: USA Margin (%) | B33: % | C33: =IFERROR(C32/C29,0) | D33: =IFERROR(D32/D29,0) | E33: =IFERROR(E32/E29,0) | F33: =IFERROR(F32/F29,0) | G33: =IFERROR(G32/G29,0) | H33: =IFERROR(H32/H29,0) | I33: =IFERROR(I32/I29,0) | J33: =IFERROR(J32/J29,0) | ... T33: =IFERROR(T32/T29,0)
A34: Apple (IAPHUB) | B34: BRL | C34: 0 | D34: 0 | E34: 0 | F34: 0 | G34: 0 | H34: 0 | I34: 0 | J34: 0 | K34: 0 | L34: 0 | M34: 0 | N34: 0 | O34: 0 | P34: 0 | Q34: 0 | R34: 0 | S34: 0 | T34: 0
A35: Apple (IAPHUB) x 0.85 | B35: BRL | C35: =C34*0.85 | D35: =D34*0.85 | E35: =E34*0.85 | F35: =F34*0.85 | G35: =G34*0.85 | H35: =H34*0.85 | I35: =I34*0.85 | J35: =J34*0.85 | ... T35: =T34*0.85
A36: Δ(%) | B36: % | C36: 0 | D36: =IFERROR((D35-C35)/C35,0) | E36: =IFERROR((E35-D35)/D35,0) | F36: =IFERROR((F35-E35)/E35,0) | G36: =IFERROR((G35-F35)/F35,0) | H36: =IFERROR((H35-G35)/G35,0) | I36: =IFERROR((I35-H35)/H35,0) | J36: =IFERROR((J35-I35)/I35,0) | K36: =IFERROR((K35-J35)/J35,0) | ... T36: =IFERROR((T35-S35)/S35,0)
A37: Apple | B37: BRL | C37: =SUMIFS(Extrato_Importado!$E:$E,Extrato_Importado!$H:$H,"2024-05",Extrato_Importado!$B:$B,"App Store Net Revenue") | D37: =SUMIFS(Extrato_Importado!$E:$E,Extrato_Importado!$H:$H,"2024-06",Extrato_Importado!$B:$B,"App Store Net Revenue") | E37: =SUMIFS(Extrato_Importado!$E:$E,Extrato_Importado!$H:$H,"2024-07",Extrato_Importado!$B:$B,"App Store Net Revenue") | F37: =SUMIFS(Extrato_Importado!$E:$E,Extrato_Importado!$H:$H,"2024-08",Extrato_Importado!$B:$B,"App Store Net Revenue") | G37: =SUMIFS(Extrato_Importado!$E:$E,Extrato_Importado!$H:$H,"2024-09",Extrato_Importado!$B:$B,"App Store Net Revenue") | H37: =SUMIFS(Extrato_Importado!$E:$E,Extrato_Importado!$H:$H,"2024-10",Extrato_Importado!$B:$B,"App Store Net Revenue") | I37: =SUMIFS(Extrato_Importado!$E:$E,Extrato_Importado!$H:$H,"2024-11",Extrato_Importado!$B:$B,"App Store Net Revenue") | J37: =SUMIFS(Extrato_Importado!$E:$E,Extrato_Importado!$H:$H,"2024-12",Extrato_Importado!$B:$B,"App Store Net Revenue") | K37: =SUMIFS(Extrato_Importado!$E:$E,Extrato_Importado!$H:$H,"2025-01",Extrato_Importado!$B:$B,"App Store Net Revenue") | L37: =SUMIFS(Extrato_Importado!$E:$E,Extrato_Importado!$H:$H,"2025-02",Extrato_Importado!$B:$B,"App Store Net Revenue") | M37: =SUMIFS(Extrato_Importado!$E:$E,Extrato_Importado!$H:$H,"2025-03",Extrato_Importado!$B:$B,"App Store Net Revenue") | N37: =SUMIFS(Extrato_Importado!$E:$E,Extrato_Importado!$H:$H,"2025-04",Extrato_Importado!$B:$B,"App Store Net Revenue") | O37: =SUMIFS(Extrato_Importado!$E:$E,Extrato_Importado!$H:$H,"2025-05",Extrato_Importado!$B:$B,"App Store Net Revenue") | P37: =SUMIFS(Extrato_Importado!$E:$E,Extrato_Importado!$H:$H,"2025-06",Extrato_Importado!$B:$B,"App Store Net Revenue") | Q37: =SUMIFS(Extrato_Importado!$E:$E,Extrato_Importado!$H:$H,"2025-07",Extrato_Importado!$B:$B,"App Store Net Revenue") | R37: =SUMIFS(Extrato_Importado!$E:$E,Extrato_Importado!$H:$H,"2025-08",Extrato_Importado!$B:$B,"App Store Net Revenue") | S37: =SUMIFS(Extrato_Importado!$E:$E,Extrato_Importado!$H:$H,"2025-09",Extrato_Importado!$B:$B,"App Store Net Revenue") | T37: =SUMIFS(Extrato_Importado!$E:$E,Extrato_Importado!$H:$H,"2025-10",Extrato_Importado!$B:$B,"App Store Net Revenue")
A38: Brazil | B38: BRL | C38: =SUMIFS(Extrato_Importado!$E:$E,Extrato_Importado!$H:$H,"2024-05",Extrato_Importado!$B:$B,"App Store Net Revenue") | D38: =SUMIFS(Extrato_Importado!$E:$E,Extrato_Importado!$H:$H,"2024-06",Extrato_Importado!$B:$B,"App Store Net Revenue") | E38: =SUMIFS(Extrato_Importado!$E:$E,Extrato_Importado!$H:$H,"2024-07",Extrato_Importado!$B:$B,"App Store Net Revenue") | F38: =SUMIFS(Extrato_Importado!$E:$E,Extrato_Importado!$H:$H,"2024-08",Extrato_Importado!$B:$B,"App Store Net Revenue") | G38: =SUMIFS(Extrato_Importado!$E:$E,Extrato_Importado!$H:$H,"2024-09",Extrato_Importado!$B:$B,"App Store Net Revenue") | H38: =SUMIFS(Extrato_Importado!$E:$E,Extrato_Importado!$H:$H,"2024-10",Extrato_Importado!$B:$B,"App Store Net Revenue") | I38: =SUMIFS(Extrato_Importado!$E:$E,Extrato_Importado!$H:$H,"2024-11",Extrato_Importado!$B:$B,"App Store Net Revenue") | J38: =SUMIFS(Extrato_Importado!$E:$E,Extrato_Importado!$H:$H,"2024-12",Extrato_Importado!$B:$B,"App Store Net Revenue") | K38: =SUMIFS(Extrato_Importado!$E:$E,Extrato_Importado!$H:$H,"2025-01",Extrato_Importado!$B:$B,"App Store Net Revenue") | L38: =SUMIFS(Extrato_Importado!$E:$E,Extrato_Importado!$H:$H,"2025-02",Extrato_Importado!$B:$B,"App Store Net Revenue") | M38: =SUMIFS(Extrato_Importado!$E:$E,Extrato_Importado!$H:$H,"2025-03",Extrato_Importado!$B:$B,"App Store Net Revenue") | N38: =SUMIFS(Extrato_Importado!$E:$E,Extrato_Importado!$H:$H,"2025-04",Extrato_Importado!$B:$B,"App Store Net Revenue") | O38: =SUMIFS(Extrato_Importado!$E:$E,Extrato_Importado!$H:$H,"2025-05",Extrato_Importado!$B:$B,"App Store Net Revenue") | P38: =SUMIFS(Extrato_Importado!$E:$E,Extrato_Importado!$H:$H,"2025-06",Extrato_Importado!$B:$B,"App Store Net Revenue") | Q38: =SUMIFS(Extrato_Importado!$E:$E,Extrato_Importado!$H:$H,"2025-07",Extrato_Importado!$B:$B,"App Store Net Revenue") | R38: =SUMIFS(Extrato_Importado!$E:$E,Extrato_Importado!$H:$H,"2025-08",Extrato_Importado!$B:$B,"App Store Net Revenue") | S38: =SUMIFS(Extrato_Importado!$E:$E,Extrato_Importado!$H:$H,"2025-09",Extrato_Importado!$B:$B,"App Store Net Revenue") | T38: =SUMIFS(Extrato_Importado!$E:$E,Extrato_Importado!$H:$H,"2025-10",Extrato_Importado!$B:$B,"App Store Net Revenue")
A39: Brazil Margin (%) | B39: % | C39: =IFERROR(C38/C37,0) | D39: =IFERROR(D38/D37,0) | E39: =IFERROR(E38/E37,0) | F39: =IFERROR(F38/F37,0) | G39: =IFERROR(G38/G37,0) | H39: =IFERROR(H38/H37,0) | I39: =IFERROR(I38/I37,0) | J39: =IFERROR(J38/J37,0) | ... T39: =IFERROR(T38/T37,0)
A40: USA | B40: BRL | C40: =SUMIFS(Extrato_Importado!$E:$E,Extrato_Importado!$H:$H,"2024-05",Extrato_Importado!$B:$B,"App Store Net Revenue") | D40: =SUMIFS(Extrato_Importado!$E:$E,Extrato_Importado!$H:$H,"2024-06",Extrato_Importado!$B:$B,"App Store Net Revenue") | E40: =SUMIFS(Extrato_Importado!$E:$E,Extrato_Importado!$H:$H,"2024-07",Extrato_Importado!$B:$B,"App Store Net Revenue") | F40: =SUMIFS(Extrato_Importado!$E:$E,Extrato_Importado!$H:$H,"2024-08",Extrato_Importado!$B:$B,"App Store Net Revenue") | G40: =SUMIFS(Extrato_Importado!$E:$E,Extrato_Importado!$H:$H,"2024-09",Extrato_Importado!$B:$B,"App Store Net Revenue") | H40: =SUMIFS(Extrato_Importado!$E:$E,Extrato_Importado!$H:$H,"2024-10",Extrato_Importado!$B:$B,"App Store Net Revenue") | I40: =SUMIFS(Extrato_Importado!$E:$E,Extrato_Importado!$H:$H,"2024-11",Extrato_Importado!$B:$B,"App Store Net Revenue") | J40: =SUMIFS(Extrato_Importado!$E:$E,Extrato_Importado!$H:$H,"2024-12",Extrato_Importado!$B:$B,"App Store Net Revenue") | K40: =SUMIFS(Extrato_Importado!$E:$E,Extrato_Importado!$H:$H,"2025-01",Extrato_Importado!$B:$B,"App Store Net Revenue") | L40: =SUMIFS(Extrato_Importado!$E:$E,Extrato_Importado!$H:$H,"2025-02",Extrato_Importado!$B:$B,"App Store Net Revenue") | M40: =SUMIFS(Extrato_Importado!$E:$E,Extrato_Importado!$H:$H,"2025-03",Extrato_Importado!$B:$B,"App Store Net Revenue") | N40: =SUMIFS(Extrato_Importado!$E:$E,Extrato_Importado!$H:$H,"2025-04",Extrato_Importado!$B:$B,"App Store Net Revenue") | O40: =SUMIFS(Extrato_Importado!$E:$E,Extrato_Importado!$H:$H,"2025-05",Extrato_Importado!$B:$B,"App Store Net Revenue") | P40: =SUMIFS(Extrato_Importado!$E:$E,Extrato_Importado!$H:$H,"2025-06",Extrato_Importado!$B:$B,"App Store Net Revenue") | Q40: =SUMIFS(Extrato_Importado!$E:$E,Extrato_Importado!$H:$H,"2025-07",Extrato_Importado!$B:$B,"App Store Net Revenue") | R40: =SUMIFS(Extrato_Importado!$E:$E,Extrato_Importado!$H:$H,"2025-08",Extrato_Importado!$B:$B,"App Store Net Revenue") | S40: =SUMIFS(Extrato_Importado!$E:$E,Extrato_Importado!$H:$H,"2025-09",Extrato_Importado!$B:$B,"App Store Net Revenue") | T40: =SUMIFS(Extrato_Importado!$E:$E,Extrato_Importado!$H:$H,"2025-10",Extrato_Importado!$B:$B,"App Store Net Revenue")
A41: USA Margin (%) | B41: % | C41: =IFERROR(C40/C37,0) | D41: =IFERROR(D40/D37,0) | E41: =IFERROR(E40/E37,0) | F41: =IFERROR(F40/F37,0) | G41: =IFERROR(G40/G37,0) | H41: =IFERROR(H40/H37,0) | I41: =IFERROR(I40/I37,0) | J41: =IFERROR(J40/J37,0) | ... T41: =IFERROR(T40/T37,0)
A42: Invest Income (rendimento de aplicação & cashback) | B42: BRL | C42: =SUMIFS(Extrato_Importado!$E:$E,Extrato_Importado!$H:$H,"2024-05",Extrato_Importado!$B:$B,"Rendimentos de Aplicações") | D42: =SUMIFS(Extrato_Importado!$E:$E,Extrato_Importado!$H:$H,"2024-06",Extrato_Importado!$B:$B,"Rendimentos de Aplicações") | E42: =SUMIFS(Extrato_Importado!$E:$E,Extrato_Importado!$H:$H,"2024-07",Extrato_Importado!$B:$B,"Rendimentos de Aplicações") | F42: =SUMIFS(Extrato_Importado!$E:$E,Extrato_Importado!$H:$H,"2024-08",Extrato_Importado!$B:$B,"Rendimentos de Aplicações") | G42: =SUMIFS(Extrato_Importado!$E:$E,Extrato_Importado!$H:$H,"2024-09",Extrato_Importado!$B:$B,"Rendimentos de Aplicações") | H42: =SUMIFS(Extrato_Importado!$E:$E,Extrato_Importado!$H:$H,"2024-10",Extrato_Importado!$B:$B,"Rendimentos de Aplicações") | I42: =SUMIFS(Extrato_Importado!$E:$E,Extrato_Importado!$H:$H,"2024-11",Extrato_Importado!$B:$B,"Rendimentos de Aplicações") | J42: =SUMIFS(Extrato_Importado!$E:$E,Extrato_Importado!$H:$H,"2024-12",Extrato_Importado!$B:$B,"Rendimentos de Aplicações") | K42: =SUMIFS(Extrato_Importado!$E:$E,Extrato_Importado!$H:$H,"2025-01",Extrato_Importado!$B:$B,"Rendimentos de Aplicações") | L42: =SUMIFS(Extrato_Importado!$E:$E,Extrato_Importado!$H:$H,"2025-02",Extrato_Importado!$B:$B,"Rendimentos de Aplicações") | M42: =SUMIFS(Extrato_Importado!$E:$E,Extrato_Importado!$H:$H,"2025-03",Extrato_Importado!$B:$B,"Rendimentos de Aplicações") | N42: =SUMIFS(Extrato_Importado!$E:$E,Extrato_Importado!$H:$H,"2025-04",Extrato_Importado!$B:$B,"Rendimentos de Aplicações") | O42: =SUMIFS(Extrato_Importado!$E:$E,Extrato_Importado!$H:$H,"2025-05",Extrato_Importado!$B:$B,"Rendimentos de Aplicações") | P42: =SUMIFS(Extrato_Importado!$E:$E,Extrato_Importado!$H:$H,"2025-06",Extrato_Importado!$B:$B,"Rendimentos de Aplicações") | Q42: =SUMIFS(Extrato_Importado!$E:$E,Extrato_Importado!$H:$H,"2025-07",Extrato_Importado!$B:$B,"Rendimentos de Aplicações") | R42: =SUMIFS(Extrato_Importado!$E:$E,Extrato_Importado!$H:$H,"2025-08",Extrato_Importado!$B:$B,"Rendimentos de Aplicações") | S42: =SUMIFS(Extrato_Importado!$E:$E,Extrato_Importado!$H:$H,"2025-09",Extrato_Importado!$B:$B,"Rendimentos de Aplicações") | T42: =SUMIFS(Extrato_Importado!$E:$E,Extrato_Importado!$H:$H,"2025-10",Extrato_Importado!$B:$B,"Rendimentos de Aplicações")
A44: Costs of Revenue | B44: BRL | C44: =C45+C46 | D44: =D45+D46 | E44: =E45+E46 | F44: =F45+F46 | G44: =G45+G46 | H44: =H45+H46 | I44: =I45+I46 | J44: =J45+J46 | ... T44: =T45+T46
A45: Payment Processing Expenses (despesas de processamento de pagamento) | B45: BRL | C45: =C25*0.1765 | D45: =D25*0.1765 | E45: =E25*0.1765 | F45: =F25*0.1765 | G45: =G25*0.1765 | H45: =H25*0.1765 | I45: =I25*0.1765 | J45: =J25*0.1765 | ... T45: =T25*0.1765
A46: COGS (CMV) | B46: BRL | C46: =SUM(C47:C52) | D46: =SUM(D47:D52) | E46: =SUM(E47:E52) | F46: =SUM(F47:F52) | G46: =SUM(G47:G52) | H46: =SUM(H47:H52) | I46: =SUM(I47:I52) | J46: =SUM(J47:J52) | ... T46: =SUM(T47:T52)
A47: AWS | B47: BRL | C47: =SUMIFS(Extrato_Importado!$E:$E,Extrato_Importado!$H:$H,"2024-05",Extrato_Importado!$B:$B,"Web Services Expenses",Extrato_Importado!$C:$C,"*AWS*") | D47: =SUMIFS(Extrato_Importado!$E:$E,Extrato_Importado!$H:$H,"2024-06",Extrato_Importado!$B:$B,"Web Services Expenses",Extrato_Importado!$C:$C,"*AWS*") | E47: =SUMIFS(Extrato_Importado!$E:$E,Extrato_Importado!$H:$H,"2024-07",Extrato_Importado!$B:$B,"Web Services Expenses",Extrato_Importado!$C:$C,"*AWS*") | F47: =SUMIFS(Extrato_Importado!$E:$E,Extrato_Importado!$H:$H,"2024-08",Extrato_Importado!$B:$B,"Web Services Expenses",Extrato_Importado!$C:$C,"*AWS*") | G47: =SUMIFS(Extrato_Importado!$E:$E,Extrato_Importado!$H:$H,"2024-09",Extrato_Importado!$B:$B,"Web Services Expenses",Extrato_Importado!$C:$C,"*AWS*") | H47: =SUMIFS(Extrato_Importado!$E:$E,Extrato_Importado!$H:$H,"2024-10",Extrato_Importado!$B:$B,"Web Services Expenses",Extrato_Importado!$C:$C,"*AWS*") | I47: =SUMIFS(Extrato_Importado!$E:$E,Extrato_Importado!$H:$H,"2024-11",Extrato_Importado!$B:$B,"Web Services Expenses",Extrato_Importado!$C:$C,"*AWS*") | J47: =SUMIFS(Extrato_Importado!$E:$E,Extrato_Importado!$H:$H,"2024-12",Extrato_Importado!$B:$B,"Web Services Expenses",Extrato_Importado!$C:$C,"*AWS*") | K47: =SUMIFS(Extrato_Importado!$E:$E,Extrato_Importado!$H:$H,"2025-01",Extrato_Importado!$B:$B,"Web Services Expenses",Extrato_Importado!$C:$C,"*AWS*") | L47: =SUMIFS(Extrato_Importado!$E:$E,Extrato_Importado!$H:$H,"2025-02",Extrato_Importado!$B:$B,"Web Services Expenses",Extrato_Importado!$C:$C,"*AWS*") | M47: =SUMIFS(Extrato_Importado!$E:$E,Extrato_Importado!$H:$H,"2025-03",Extrato_Importado!$B:$B,"Web Services Expenses",Extrato_Importado!$C:$C,"*AWS*") | N47: =SUMIFS(Extrato_Importado!$E:$E,Extrato_Importado!$H:$H,"2025-04",Extrato_Importado!$B:$B,"Web Services Expenses",Extrato_Importado!$C:$C,"*AWS*") | O47: =SUMIFS(Extrato_Importado!$E:$E,Extrato_Importado!$H:$H,"2025-05",Extrato_Importado!$B:$B,"Web Services Expenses",Extrato_Importado!$C:$C,"*AWS*") | P47: =SUMIFS(Extrato_Importado!$E:$E,Extrato_Importado!$H:$H,"2025-06",Extrato_Importado!$B:$B,"Web Services Expenses",Extrato_Importado!$C:$C,"*AWS*") | Q47: =SUMIFS(Extrato_Importado!$E:$E,Extrato_Importado!$H:$H,"2025-07",Extrato_Importado!$B:$B,"Web Services Expenses",Extrato_Importado!$C:$C,"*AWS*") | R47: =SUMIFS(Extrato_Importado!$E:$E,Extrato_Importado!$H:$H,"2025-08",Extrato_Importado!$B:$B,"Web Services Expenses",Extrato_Importado!$C:$C,"*AWS*") | S47: =SUMIFS(Extrato_Importado!$E:$E,Extrato_Importado!$H:$H,"2025-09",Extrato_Importado!$B:$B,"Web Services Expenses",Extrato_Importado!$C:$C,"*AWS*") | T47: =SUMIFS(Extrato_Importado!$E:$E,Extrato_Importado!$H:$H,"2025-10",Extrato_Importado!$B:$B,"Web Services Expenses",Extrato_Importado!$C:$C,"*AWS*")
A48: Cloudflare | B48: BRL | C48: =SUMIFS(Extrato_Importado!$E:$E,Extrato_Importado!$H:$H,"2024-05",Extrato_Importado!$B:$B,"Web Services Expenses",Extrato_Importado!$C:$C,"*Cloudflare*") | D48: =SUMIFS(Extrato_Importado!$E:$E,Extrato_Importado!$H:$H,"2024-06",Extrato_Importado!$B:$B,"Web Services Expenses",Extrato_Importado!$C:$C,"*Cloudflare*") | E48: =SUMIFS(Extrato_Importado!$E:$E,Extrato_Importado!$H:$H,"2024-07",Extrato_Importado!$B:$B,"Web Services Expenses",Extrato_Importado!$C:$C,"*Cloudflare*") | F48: =SUMIFS(Extrato_Importado!$E:$E,Extrato_Importado!$H:$H,"2024-08",Extrato_Importado!$B:$B,"Web Services Expenses",Extrato_Importado!$C:$C,"*Cloudflare*") | G48: =SUMIFS(Extrato_Importado!$E:$E,Extrato_Importado!$H:$H,"2024-09",Extrato_Importado!$B:$B,"Web Services Expenses",Extrato_Importado!$C:$C,"*Cloudflare*") | H48: =SUMIFS(Extrato_Importado!$E:$E,Extrato_Importado!$H:$H,"2024-10",Extrato_Importado!$B:$B,"Web Services Expenses",Extrato_Importado!$C:$C,"*Cloudflare*") | I48: =SUMIFS(Extrato_Importado!$E:$E,Extrato_Importado!$H:$H,"2024-11",Extrato_Importado!$B:$B,"Web Services Expenses",Extrato_Importado!$C:$C,"*Cloudflare*") | J48: =SUMIFS(Extrato_Importado!$E:$E,Extrato_Importado!$H:$H,"2024-12",Extrato_Importado!$B:$B,"Web Services Expenses",Extrato_Importado!$C:$C,"*Cloudflare*") | K48: =SUMIFS(Extrato_Importado!$E:$E,Extrato_Importado!$H:$H,"2025-01",Extrato_Importado!$B:$B,"Web Services Expenses",Extrato_Importado!$C:$C,"*Cloudflare*") | L48: =SUMIFS(Extrato_Importado!$E:$E,Extrato_Importado!$H:$H,"2025-02",Extrato_Importado!$B:$B,"Web Services Expenses",Extrato_Importado!$C:$C,"*Cloudflare*") | M48: =SUMIFS(Extrato_Importado!$E:$E,Extrato_Importado!$H:$H,"2025-03",Extrato_Importado!$B:$B,"Web Services Expenses",Extrato_Importado!$C:$C,"*Cloudflare*") | N48: =SUMIFS(Extrato_Importado!$E:$E,Extrato_Importado!$H:$H,"2025-04",Extrato_Importado!$B:$B,"Web Services Expenses",Extrato_Importado!$C:$C,"*Cloudflare*") | O48: =SUMIFS(Extrato_Importado!$E:$E,Extrato_Importado!$H:$H,"2025-05",Extrato_Importado!$B:$B,"Web Services Expenses",Extrato_Importado!$C:$C,"*Cloudflare*") | P48: =SUMIFS(Extrato_Importado!$E:$E,Extrato_Importado!$H:$H,"2025-06",Extrato_Importado!$B:$B,"Web Services Expenses",Extrato_Importado!$C:$C,"*Cloudflare*") | Q48: =SUMIFS(Extrato_Importado!$E:$E,Extrato_Importado!$H:$H,"2025-07",Extrato_Importado!$B:$B,"Web Services Expenses",Extrato_Importado!$C:$C,"*Cloudflare*") | R48: =SUMIFS(Extrato_Importado!$E:$E,Extrato_Importado!$H:$H,"2025-08",Extrato_Importado!$B:$B,"Web Services Expenses",Extrato_Importado!$C:$C,"*Cloudflare*") | S48: =SUMIFS(Extrato_Importado!$E:$E,Extrato_Importado!$H:$H,"2025-09",Extrato_Importado!$B:$B,"Web Services Expenses",Extrato_Importado!$C:$C,"*Cloudflare*") | T48: =SUMIFS(Extrato_Importado!$E:$E,Extrato_Importado!$H:$H,"2025-10",Extrato_Importado!$B:$B,"Web Services Expenses",Extrato_Importado!$C:$C,"*Cloudflare*")
A49: Heroku | B49: BRL | C49: =SUMIFS(Extrato_Importado!$E:$E,Extrato_Importado!$H:$H,"2024-05",Extrato_Importado!$B:$B,"Web Services Expenses",Extrato_Importado!$C:$C,"*Heroku*") | D49: =SUMIFS(Extrato_Importado!$E:$E,Extrato_Importado!$H:$H,"2024-06",Extrato_Importado!$B:$B,"Web Services Expenses",Extrato_Importado!$C:$C,"*Heroku*") | E49: =SUMIFS(Extrato_Importado!$E:$E,Extrato_Importado!$H:$H,"2024-07",Extrato_Importado!$B:$B,"Web Services Expenses",Extrato_Importado!$C:$C,"*Heroku*") | F49: =SUMIFS(Extrato_Importado!$E:$E,Extrato_Importado!$H:$H,"2024-08",Extrato_Importado!$B:$B,"Web Services Expenses",Extrato_Importado!$C:$C,"*Heroku*") | G49: =SUMIFS(Extrato_Importado!$E:$E,Extrato_Importado!$H:$H,"2024-09",Extrato_Importado!$B:$B,"Web Services Expenses",Extrato_Importado!$C:$C,"*Heroku*") | H49: =SUMIFS(Extrato_Importado!$E:$E,Extrato_Importado!$H:$H,"2024-10",Extrato_Importado!$B:$B,"Web Services Expenses",Extrato_Importado!$C:$C,"*Heroku*") | I49: =SUMIFS(Extrato_Importado!$E:$E,Extrato_Importado!$H:$H,"2024-11",Extrato_Importado!$B:$B,"Web Services Expenses",Extrato_Importado!$C:$C,"*Heroku*") | J49: =SUMIFS(Extrato_Importado!$E:$E,Extrato_Importado!$H:$H,"2024-12",Extrato_Importado!$B:$B,"Web Services Expenses",Extrato_Importado!$C:$C,"*Heroku*") | K49: =SUMIFS(Extrato_Importado!$E:$E,Extrato_Importado!$H:$H,"2025-01",Extrato_Importado!$B:$B,"Web Services Expenses",Extrato_Importado!$C:$C,"*Heroku*") | L49: =SUMIFS(Extrato_Importado!$E:$E,Extrato_Importado!$H:$H,"2025-02",Extrato_Importado!$B:$B,"Web Services Expenses",Extrato_Importado!$C:$C,"*Heroku*") | M49: =SUMIFS(Extrato_Importado!$E:$E,Extrato_Importado!$H:$H,"2025-03",Extrato_Importado!$B:$B,"Web Services Expenses",Extrato_Importado!$C:$C,"*Heroku*") | N49: =SUMIFS(Extrato_Importado!$E:$E,Extrato_Importado!$H:$H,"2025-04",Extrato_Importado!$B:$B,"Web Services Expenses",Extrato_Importado!$C:$C,"*Heroku*") | O49: =SUMIFS(Extrato_Importado!$E:$E,Extrato_Importado!$H:$H,"2025-05",Extrato_Importado!$B:$B,"Web Services Expenses",Extrato_Importado!$C:$C,"*Heroku*") | P49: =SUMIFS(Extrato_Importado!$E:$E,Extrato_Importado!$H:$H,"2025-06",Extrato_Importado!$B:$B,"Web Services Expenses",Extrato_Importado!$C:$C,"*Heroku*") | Q49: =SUMIFS(Extrato_Importado!$E:$E,Extrato_Importado!$H:$H,"2025-07",Extrato_Importado!$B:$B,"Web Services Expenses",Extrato_Importado!$C:$C,"*Heroku*") | R49: =SUMIFS(Extrato_Importado!$E:$E,Extrato_Importado!$H:$H,"2025-08",Extrato_Importado!$B:$B,"Web Services Expenses",Extrato_Importado!$C:$C,"*Heroku*") | S49: =SUMIFS(Extrato_Importado!$E:$E,Extrato_Importado!$H:$H,"2025-09",Extrato_Importado!$B:$B,"Web Services Expenses",Extrato_Importado!$C:$C,"*Heroku*") | T49: =SUMIFS(Extrato_Importado!$E:$E,Extrato_Importado!$H:$H,"2025-10",Extrato_Importado!$B:$B,"Web Services Expenses",Extrato_Importado!$C:$C,"*Heroku*")
A50: IAPHUB | B50: BRL | C50: =SUMIFS(Extrato_Importado!$E:$E,Extrato_Importado!$H:$H,"2024-05",Extrato_Importado!$B:$B,"Web Services Expenses",Extrato_Importado!$C:$C,"*IAPHUB*") | D50: =SUMIFS(Extrato_Importado!$E:$E,Extrato_Importado!$H:$H,"2024-06",Extrato_Importado!$B:$B,"Web Services Expenses",Extrato_Importado!$C:$C,"*IAPHUB*") | E50: =SUMIFS(Extrato_Importado!$E:$E,Extrato_Importado!$H:$H,"2024-07",Extrato_Importado!$B:$B,"Web Services Expenses",Extrato_Importado!$C:$C,"*IAPHUB*") | F50: =SUMIFS(Extrato_Importado!$E:$E,Extrato_Importado!$H:$H,"2024-08",Extrato_Importado!$B:$B,"Web Services Expenses",Extrato_Importado!$C:$C,"*IAPHUB*") | G50: =SUMIFS(Extrato_Importado!$E:$E,Extrato_Importado!$H:$H,"2024-09",Extrato_Importado!$B:$B,"Web Services Expenses",Extrato_Importado!$C:$C,"*IAPHUB*") | H50: =SUMIFS(Extrato_Importado!$E:$E,Extrato_Importado!$H:$H,"2024-10",Extrato_Importado!$B:$B,"Web Services Expenses",Extrato_Importado!$C:$C,"*IAPHUB*") | I50: =SUMIFS(Extrato_Importado!$E:$E,Extrato_Importado!$H:$H,"2024-11",Extrato_Importado!$B:$B,"Web Services Expenses",Extrato_Importado!$C:$C,"*IAPHUB*") | J50: =SUMIFS(Extrato_Importado!$E:$E,Extrato_Importado!$H:$H,"2024-12",Extrato_Importado!$B:$B,"Web Services Expenses",Extrato_Importado!$C:$C,"*IAPHUB*") | K50: =SUMIFS(Extrato_Importado!$E:$E,Extrato_Importado!$H:$H,"2025-01",Extrato_Importado!$B:$B,"Web Services Expenses",Extrato_Importado!$C:$C,"*IAPHUB*") | L50: =SUMIFS(Extrato_Importado!$E:$E,Extrato_Importado!$H:$H,"2025-02",Extrato_Importado!$B:$B,"Web Services Expenses",Extrato_Importado!$C:$C,"*IAPHUB*") | M50: =SUMIFS(Extrato_Importado!$E:$E,Extrato_Importado!$H:$H,"2025-03",Extrato_Importado!$B:$B,"Web Services Expenses",Extrato_Importado!$C:$C,"*IAPHUB*") | N50: =SUMIFS(Extrato_Importado!$E:$E,Extrato_Importado!$H:$H,"2025-04",Extrato_Importado!$B:$B,"Web Services Expenses",Extrato_Importado!$C:$C,"*IAPHUB*") | O50: =SUMIFS(Extrato_Importado!$E:$E,Extrato_Importado!$H:$H,"2025-05",Extrato_Importado!$B:$B,"Web Services Expenses",Extrato_Importado!$C:$C,"*IAPHUB*") | P50: =SUMIFS(Extrato_Importado!$E:$E,Extrato_Importado!$H:$H,"2025-06",Extrato_Importado!$B:$B,"Web Services Expenses",Extrato_Importado!$C:$C,"*IAPHUB*") | Q50: =SUMIFS(Extrato_Importado!$E:$E,Extrato_Importado!$H:$H,"2025-07",Extrato_Importado!$B:$B,"Web Services Expenses",Extrato_Importado!$C:$C,"*IAPHUB*") | R50: =SUMIFS(Extrato_Importado!$E:$E,Extrato_Importado!$H:$H,"2025-08",Extrato_Importado!$B:$B,"Web Services Expenses",Extrato_Importado!$C:$C,"*IAPHUB*") | S50: =SUMIFS(Extrato_Importado!$E:$E,Extrato_Importado!$H:$H,"2025-09",Extrato_Importado!$B:$B,"Web Services Expenses",Extrato_Importado!$C:$C,"*IAPHUB*") | T50: =SUMIFS(Extrato_Importado!$E:$E,Extrato_Importado!$H:$H,"2025-10",Extrato_Importado!$B:$B,"Web Services Expenses",Extrato_Importado!$C:$C,"*IAPHUB*")
A51: MailGun | B51: BRL | C51: =SUMIFS(Extrato_Importado!$E:$E,Extrato_Importado!$H:$H,"2024-05",Extrato_Importado!$B:$B,"Web Services Expenses",Extrato_Importado!$C:$C,"*MailGun*") | D51: =SUMIFS(Extrato_Importado!$E:$E,Extrato_Importado!$H:$H,"2024-06",Extrato_Importado!$B:$B,"Web Services Expenses",Extrato_Importado!$C:$C,"*MailGun*") | E51: =SUMIFS(Extrato_Importado!$E:$E,Extrato_Importado!$H:$H,"2024-07",Extrato_Importado!$B:$B,"Web Services Expenses",Extrato_Importado!$C:$C,"*MailGun*") | F51: =SUMIFS(Extrato_Importado!$E:$E,Extrato_Importado!$H:$H,"2024-08",Extrato_Importado!$B:$B,"Web Services Expenses",Extrato_Importado!$C:$C,"*MailGun*") | G51: =SUMIFS(Extrato_Importado!$E:$E,Extrato_Importado!$H:$H,"2024-09",Extrato_Importado!$B:$B,"Web Services Expenses",Extrato_Importado!$C:$C,"*MailGun*") | H51: =SUMIFS(Extrato_Importado!$E:$E,Extrato_Importado!$H:$H,"2024-10",Extrato_Importado!$B:$B,"Web Services Expenses",Extrato_Importado!$C:$C,"*MailGun*") | I51: =SUMIFS(Extrato_Importado!$E:$E,Extrato_Importado!$H:$H,"2024-11",Extrato_Importado!$B:$B,"Web Services Expenses",Extrato_Importado!$C:$C,"*MailGun*") | J51: =SUMIFS(Extrato_Importado!$E:$E,Extrato_Importado!$H:$H,"2024-12",Extrato_Importado!$B:$B,"Web Services Expenses",Extrato_Importado!$C:$C,"*MailGun*") | K51: =SUMIFS(Extrato_Importado!$E:$E,Extrato_Importado!$H:$H,"2025-01",Extrato_Importado!$B:$B,"Web Services Expenses",Extrato_Importado!$C:$C,"*MailGun*") | L51: =SUMIFS(Extrato_Importado!$E:$E,Extrato_Importado!$H:$H,"2025-02",Extrato_Importado!$B:$B,"Web Services Expenses",Extrato_Importado!$C:$C,"*MailGun*") | M51: =SUMIFS(Extrato_Importado!$E:$E,Extrato_Importado!$H:$H,"2025-03",Extrato_Importado!$B:$B,"Web Services Expenses",Extrato_Importado!$C:$C,"*MailGun*") | N51: =SUMIFS(Extrato_Importado!$E:$E,Extrato_Importado!$H:$H,"2025-04",Extrato_Importado!$B:$B,"Web Services Expenses",Extrato_Importado!$C:$C,"*MailGun*") | O51: =SUMIFS(Extrato_Importado!$E:$E,Extrato_Importado!$H:$H,"2025-05",Extrato_Importado!$B:$B,"Web Services Expenses",Extrato_Importado!$C:$C,"*MailGun*") | P51: =SUMIFS(Extrato_Importado!$E:$E,Extrato_Importado!$H:$H,"2025-06",Extrato_Importado!$B:$B,"Web Services Expenses",Extrato_Importado!$C:$C,"*MailGun*") | Q51: =SUMIFS(Extrato_Importado!$E:$E,Extrato_Importado!$H:$H,"2025-07",Extrato_Importado!$B:$B,"Web Services Expenses",Extrato_Importado!$C:$C,"*MailGun*") | R51: =SUMIFS(Extrato_Importado!$E:$E,Extrato_Importado!$H:$H,"2025-08",Extrato_Importado!$B:$B,"Web Services Expenses",Extrato_Importado!$C:$C,"*MailGun*") | S51: =SUMIFS(Extrato_Importado!$E:$E,Extrato_Importado!$H:$H,"2025-09",Extrato_Importado!$B:$B,"Web Services Expenses",Extrato_Importado!$C:$C,"*MailGun*") | T51: =SUMIFS(Extrato_Importado!$E:$E,Extrato_Importado!$H:$H,"2025-10",Extrato_Importado!$B:$B,"Web Services Expenses",Extrato_Importado!$C:$C,"*MailGun*")
A52: AWS SES | B52: BRL | C52: =SUMIFS(Extrato_Importado!$E:$E,Extrato_Importado!$H:$H,"2024-05",Extrato_Importado!$B:$B,"Web Services Expenses",Extrato_Importado!$C:$C,"*AWS SES*") | D52: =SUMIFS(Extrato_Importado!$E:$E,Extrato_Importado!$H:$H,"2024-06",Extrato_Importado!$B:$B,"Web Services Expenses",Extrato_Importado!$C:$C,"*AWS SES*") | E52: =SUMIFS(Extrato_Importado!$E:$E,Extrato_Importado!$H:$H,"2024-07",Extrato_Importado!$B:$B,"Web Services Expenses",Extrato_Importado!$C:$C,"*AWS SES*") | F52: =SUMIFS(Extrato_Importado!$E:$E,Extrato_Importado!$H:$H,"2024-08",Extrato_Importado!$B:$B,"Web Services Expenses",Extrato_Importado!$C:$C,"*AWS SES*") | G52: =SUMIFS(Extrato_Importado!$E:$E,Extrato_Importado!$H:$H,"2024-09",Extrato_Importado!$B:$B,"Web Services Expenses",Extrato_Importado!$C:$C,"*AWS SES*") | H52: =SUMIFS(Extrato_Importado!$E:$E,Extrato_Importado!$H:$H,"2024-10",Extrato_Importado!$B:$B,"Web Services Expenses",Extrato_Importado!$C:$C,"*AWS SES*") | I52: =SUMIFS(Extrato_Importado!$E:$E,Extrato_Importado!$H:$H,"2024-11",Extrato_Importado!$B:$B,"Web Services Expenses",Extrato_Importado!$C:$C,"*AWS SES*") | J52: =SUMIFS(Extrato_Importado!$E:$E,Extrato_Importado!$H:$H,"2024-12",Extrato_Importado!$B:$B,"Web Services Expenses",Extrato_Importado!$C:$C,"*AWS SES*") | K52: =SUMIFS(Extrato_Importado!$E:$E,Extrato_Importado!$H:$H,"2025-01",Extrato_Importado!$B:$B,"Web Services Expenses",Extrato_Importado!$C:$C,"*AWS SES*") | L52: =SUMIFS(Extrato_Importado!$E:$E,Extrato_Importado!$H:$H,"2025-02",Extrato_Importado!$B:$B,"Web Services Expenses",Extrato_Importado!$C:$C,"*AWS SES*") | M52: =SUMIFS(Extrato_Importado!$E:$E,Extrato_Importado!$H:$H,"2025-03",Extrato_Importado!$B:$B,"Web Services Expenses",Extrato_Importado!$C:$C,"*AWS SES*") | N52: =SUMIFS(Extrato_Importado!$E:$E,Extrato_Importado!$H:$H,"2025-04",Extrato_Importado!$B:$B,"Web Services Expenses",Extrato_Importado!$C:$C,"*AWS SES*") | O52: =SUMIFS(Extrato_Importado!$E:$E,Extrato_Importado!$H:$H,"2025-05",Extrato_Importado!$B:$B,"Web Services Expenses",Extrato_Importado!$C:$C,"*AWS SES*") | P52: =SUMIFS(Extrato_Importado!$E:$E,Extrato_Importado!$H:$H,"2025-06",Extrato_Importado!$B:$B,"Web Services Expenses",Extrato_Importado!$C:$C,"*AWS SES*") | Q52: =SUMIFS(Extrato_Importado!$E:$E,Extrato_Importado!$H:$H,"2025-07",Extrato_Importado!$B:$B,"Web Services Expenses",Extrato_Importado!$C:$C,"*AWS SES*") | R52: =SUMIFS(Extrato_Importado!$E:$E,Extrato_Importado!$H:$H,"2025-08",Extrato_Importado!$B:$B,"Web Services Expenses",Extrato_Importado!$C:$C,"*AWS SES*") | S52: =SUMIFS(Extrato_Importado!$E:$E,Extrato_Importado!$H:$H,"2025-09",Extrato_Importado!$B:$B,"Web Services Expenses",Extrato_Importado!$C:$C,"*AWS SES*") | T52: =SUMIFS(Extrato_Importado!$E:$E,Extrato_Importado!$H:$H,"2025-10",Extrato_Importado!$B:$B,"Web Services Expenses",Extrato_Importado!$C:$C,"*AWS SES*")
A54: Gross Profit | B54: BRL | C54: =C24-C44 | D54: =D24-D44 | E54: =E24-E44 | F54: =F24-F44 | G54: =G24-G44 | H54: =H24-H44 | I54: =I24-I44 | J54: =J24-J44 | ... T54: =T24-T44
A55: Gross Margin | B55: % | C55: =IFERROR(C54/C24,0) | D55: =IFERROR(D54/D24,0) | E55: =IFERROR(E54/E24,0) | F55: =IFERROR(F54/F24,0) | G55: =IFERROR(G54/G24,0) | H55: =IFERROR(H54/H24,0) | I55: =IFERROR(I54/I24,0) | J55: =IFERROR(J54/J24,0) | ... T55: =IFERROR(T54/T24,0)
A57: Operating Expenses (Despesas Administrativas e Vendas Gerais) | B57: BRL | C57: =C58+C59 | D57: =D58+D59 | E57: =E58+E59 | F57: =F58+F59 | G57: =G58+G59 | H57: =H58+H59 | I57: =I58+I59 | J57: =J58+J59 | ... T57: =T58+T59
A58: R&D | B58: BRL | C58: 0 | D58: 0 | E58: 0 | F58: 0 | G58: 0 | H58: 0 | I58: 0 | J58: 0 | K58: 0 | L58: 0 | M58: 0 | N58: 0 | O58: 0 | P58: 0 | Q58: 0 | R58: 0 | S58: 0 | T58: 0
A59: SG&A | B59: BRL | C59: =C60+C68+C69 | D59: =D60+D68+D69 | E59: =E60+E68+E69 | F59: =F60+F68+F69 | G59: =G60+G68+G69 | H59: =H60+H68+H69 | I59: =I60+I68+I69 | J59: =J60+J68+J69 | ... T59: =T60+T68+T69
A60: Marketing | B60: BRL | C60: =SUMIFS(Extrato_Importado!$E:$E,Extrato_Importado!$H:$H,"2024-05",Extrato_Importado!$B:$B,"Marketing & Growth Expenses") | D60: =SUMIFS(Extrato_Importado!$E:$E,Extrato_Importado!$H:$H,"2024-06",Extrato_Importado!$B:$B,"Marketing & Growth Expenses") | E60: =SUMIFS(Extrato_Importado!$E:$E,Extrato_Importado!$H:$H,"2024-07",Extrato_Importado!$B:$B,"Marketing & Growth Expenses") | F60: =SUMIFS(Extrato_Importado!$E:$E,Extrato_Importado!$H:$H,"2024-08",Extrato_Importado!$B:$B,"Marketing & Growth Expenses") | G60: =SUMIFS(Extrato_Importado!$E:$E,Extrato_Importado!$H:$H,"2024-09",Extrato_Importado!$B:$B,"Marketing & Growth Expenses") | H60: =SUMIFS(Extrato_Importado!$E:$E,Extrato_Importado!$H:$H,"2024-10",Extrato_Importado!$B:$B,"Marketing & Growth Expenses") | I60: =SUMIFS(Extrato_Importado!$E:$E,Extrato_Importado!$H:$H,"2024-11",Extrato_Importado!$B:$B,"Marketing & Growth Expenses") | J60: =SUMIFS(Extrato_Importado!$E:$E,Extrato_Importado!$H:$H,"2024-12",Extrato_Importado!$B:$B,"Marketing & Growth Expenses") | K60: =SUMIFS(Extrato_Importado!$E:$E,Extrato_Importado!$H:$H,"2025-01",Extrato_Importado!$B:$B,"Marketing & Growth Expenses") | L60: =SUMIFS(Extrato_Importado!$E:$E,Extrato_Importado!$H:$H,"2025-02",Extrato_Importado!$B:$B,"Marketing & Growth Expenses") | M60: =SUMIFS(Extrato_Importado!$E:$E,Extrato_Importado!$H:$H,"2025-03",Extrato_Importado!$B:$B,"Marketing & Growth Expenses") | N60: =SUMIFS(Extrato_Importado!$E:$E,Extrato_Importado!$H:$H,"2025-04",Extrato_Importado!$B:$B,"Marketing & Growth Expenses") | O60: =SUMIFS(Extrato_Importado!$E:$E,Extrato_Importado!$H:$H,"2025-05",Extrato_Importado!$B:$B,"Marketing & Growth Expenses") | P60: =SUMIFS(Extrato_Importado!$E:$E,Extrato_Importado!$H:$H,"2025-06",Extrato_Importado!$B:$B,"Marketing & Growth Expenses") | Q60: =SUMIFS(Extrato_Importado!$E:$E,Extrato_Importado!$H:$H,"2025-07",Extrato_Importado!$B:$B,"Marketing & Growth Expenses") | R60: =SUMIFS(Extrato_Importado!$E:$E,Extrato_Importado!$H:$H,"2025-08",Extrato_Importado!$B:$B,"Marketing & Growth Expenses") | S60: =SUMIFS(Extrato_Importado!$E:$E,Extrato_Importado!$H:$H,"2025-09",Extrato_Importado!$B:$B,"Marketing & Growth Expenses") | T60: =SUMIFS(Extrato_Importado!$E:$E,Extrato_Importado!$H:$H,"2025-10",Extrato_Importado!$B:$B,"Marketing & Growth Expenses")
A61: Marketing/Revenue no Tax | B61: % | C61: =IFERROR(C60/C25,0) | D61: =IFERROR(D60/D25,0) | E61: =IFERROR(E60/E25,0) | F61: =IFERROR(F60/F25,0) | G61: =IFERROR(G60/G25,0) | H61: =IFERROR(H60/H25,0) | I61: =IFERROR(I60/I25,0) | J61: =IFERROR(J60/J25,0) | ... T61: =IFERROR(T60/T25,0)
A62: EaM - BR | B62: BRL | C62: 0 | D62: 0 | E62: 0 | F62: 0 | G62: 0 | H62: 0 | I62: 0 | J62: 0 | K62: 0 | L62: 0 | M62: 0 | N62: 0 | O62: 0 | P62: 0 | Q62: 0 | R62: 0 | S62: 0 | T62: 0
A63: EaM - US | B63: BRL | C63: 0 | D63: 0 | E63: 0 | F63: 0 | G63: 0 | H63: 0 | I63: 0 | J63: 0 | K63: 0 | L63: 0 | M63: 0 | N63: 0 | O63: 0 | P63: 0 | Q63: 0 | R63: 0 | S63: 0 | T63: 0
A64: Affiliates & Events | B64: BRL | C64: 0 | D64: 0 | E64: 0 | F64: 0 | G64: 0 | H64: 0 | I64: 0 | J64: 0 | K64: 0 | L64: 0 | M64: 0 | N64: 0 | O64: 0 | P64: 0 | Q64: 0 | R64: 0 | S64: 0 | T64: 0
A65: Google Ads | B65: BRL | C65: 0 | D65: 0 | E65: 0 | F65: 0 | G65: 0 | H65: 0 | I65: 0 | J65: 0 | K65: 0 | L65: 0 | M65: 0 | N65: 0 | O65: 0 | P65: 0 | Q65: 0 | R65: 0 | S65: 0 | T65: 0
A66: Apple Search Ads (ASA) | B66: BRL | C66: 0 | D66: 0 | E66: 0 | F66: 0 | G66: 0 | H66: 0 | I66: 0 | J66: 0 | K66: 0 | L66: 0 | M66: 0 | N66: 0 | O66: 0 | P66: 0 | Q66: 0 | R66: 0 | S66: 0 | T66: 0
A67: Meta Ads | B67: BRL | C67: 0 | D67: 0 | E67: 0 | F67: 0 | G67: 0 | H67: 0 | I67: 0 | J67: 0 | K67: 0 | L67: 0 | M67: 0 | N67: 0 | O67: 0 | P67: 0 | Q67: 0 | R67: 0 | S67: 0 | T67: 0
A68: Wages | B68: BRL | C68: =SUMIFS(Extrato_Importado!$E:$E,Extrato_Importado!$H:$H,"2024-05",Extrato_Importado!$B:$B,"Wages Expenses") | D68: =SUMIFS(Extrato_Importado!$E:$E,Extrato_Importado!$H:$H,"2024-06",Extrato_Importado!$B:$B,"Wages Expenses") | E68: =SUMIFS(Extrato_Importado!$E:$E,Extrato_Importado!$H:$H,"2024-07",Extrato_Importado!$B:$B,"Wages Expenses") | F68: =SUMIFS(Extrato_Importado!$E:$E,Extrato_Importado!$H:$H,"2024-08",Extrato_Importado!$B:$B,"Wages Expenses") | G68: =SUMIFS(Extrato_Importado!$E:$E,Extrato_Importado!$H:$H,"2024-09",Extrato_Importado!$B:$B,"Wages Expenses") | H68: =SUMIFS(Extrato_Importado!$E:$E,Extrato_Importado!$H:$H,"2024-10",Extrato_Importado!$B:$B,"Wages Expenses") | I68: =SUMIFS(Extrato_Importado!$E:$E,Extrato_Importado!$H:$H,"2024-11",Extrato_Importado!$B:$B,"Wages Expenses") | J68: =SUMIFS(Extrato_Importado!$E:$E,Extrato_Importado!$H:$H,"2024-12",Extrato_Importado!$B:$B,"Wages Expenses") | K68: =SUMIFS(Extrato_Importado!$E:$E,Extrato_Importado!$H:$H,"2025-01",Extrato_Importado!$B:$B,"Wages Expenses") | L68: =SUMIFS(Extrato_Importado!$E:$E,Extrato_Importado!$H:$H,"2025-02",Extrato_Importado!$B:$B,"Wages Expenses") | M68: =SUMIFS(Extrato_Importado!$E:$E,Extrato_Importado!$H:$H,"2025-03",Extrato_Importado!$B:$B,"Wages Expenses") | N68: =SUMIFS(Extrato_Importado!$E:$E,Extrato_Importado!$H:$H,"2025-04",Extrato_Importado!$B:$B,"Wages Expenses") | O68: =SUMIFS(Extrato_Importado!$E:$E,Extrato_Importado!$H:$H,"2025-05",Extrato_Importado!$B:$B,"Wages Expenses") | P68: =SUMIFS(Extrato_Importado!$E:$E,Extrato_Importado!$H:$H,"2025-06",Extrato_Importado!$B:$B,"Wages Expenses") | Q68: =SUMIFS(Extrato_Importado!$E:$E,Extrato_Importado!$H:$H,"2025-07",Extrato_Importado!$B:$B,"Wages Expenses") | R68: =SUMIFS(Extrato_Importado!$E:$E,Extrato_Importado!$H:$H,"2025-08",Extrato_Importado!$B:$B,"Wages Expenses") | S68: =SUMIFS(Extrato_Importado!$E:$E,Extrato_Importado!$H:$H,"2025-09",Extrato_Importado!$B:$B,"Wages Expenses") | T68: =SUMIFS(Extrato_Importado!$E:$E,Extrato_Importado!$H:$H,"2025-10",Extrato_Importado!$B:$B,"Wages Expenses")
A69: Tech Support & Services | B69: BRL | C69: =SUMIFS(Extrato_Importado!$E:$E,Extrato_Importado!$H:$H,"2024-05",Extrato_Importado!$B:$B,"Tech Support & Services") | D69: =SUMIFS(Extrato_Importado!$E:$E,Extrato_Importado!$H:$H,"2024-06",Extrato_Importado!$B:$B,"Tech Support & Services") | E69: =SUMIFS(Extrato_Importado!$E:$E,Extrato_Importado!$H:$H,"2024-07",Extrato_Importado!$B:$B,"Tech Support & Services") | F69: =SUMIFS(Extrato_Importado!$E:$E,Extrato_Importado!$H:$H,"2024-08",Extrato_Importado!$B:$B,"Tech Support & Services") | G69: =SUMIFS(Extrato_Importado!$E:$E,Extrato_Importado!$H:$H,"2024-09",Extrato_Importado!$B:$B,"Tech Support & Services") | H69: =SUMIFS(Extrato_Importado!$E:$E,Extrato_Importado!$H:$H,"2024-10",Extrato_Importado!$B:$B,"Tech Support & Services") | I69: =SUMIFS(Extrato_Importado!$E:$E,Extrato_Importado!$H:$H,"2024-11",Extrato_Importado!$B:$B,"Tech Support & Services") | J69: =SUMIFS(Extrato_Importado!$E:$E,Extrato_Importado!$H:$H,"2024-12",Extrato_Importado!$B:$B,"Tech Support & Services") | K69: =SUMIFS(Extrato_Importado!$E:$E,Extrato_Importado!$H:$H,"2025-01",Extrato_Importado!$B:$B,"Tech Support & Services") | L69: =SUMIFS(Extrato_Importado!$E:$E,Extrato_Importado!$H:$H,"2025-02",Extrato_Importado!$B:$B,"Tech Support & Services") | M69: =SUMIFS(Extrato_Importado!$E:$E,Extrato_Importado!$H:$H,"2025-03",Extrato_Importado!$B:$B,"Tech Support & Services") | N69: =SUMIFS(Extrato_Importado!$E:$E,Extrato_Importado!$H:$H,"2025-04",Extrato_Importado!$B:$B,"Tech Support & Services") | O69: =SUMIFS(Extrato_Importado!$E:$E,Extrato_Importado!$H:$H,"2025-05",Extrato_Importado!$B:$B,"Tech Support & Services") | P69: =SUMIFS(Extrato_Importado!$E:$E,Extrato_Importado!$H:$H,"2025-06",Extrato_Importado!$B:$B,"Tech Support & Services") | Q69: =SUMIFS(Extrato_Importado!$E:$E,Extrato_Importado!$H:$H,"2025-07",Extrato_Importado!$B:$B,"Tech Support & Services") | R69: =SUMIFS(Extrato_Importado!$E:$E,Extrato_Importado!$H:$H,"2025-08",Extrato_Importado!$B:$B,"Tech Support & Services") | S69: =SUMIFS(Extrato_Importado!$E:$E,Extrato_Importado!$H:$H,"2025-09",Extrato_Importado!$B:$B,"Tech Support & Services") | T69: =SUMIFS(Extrato_Importado!$E:$E,Extrato_Importado!$H:$H,"2025-10",Extrato_Importado!$B:$B,"Tech Support & Services")
A70: Conta Azul | B70: BRL | C70: 0 | D70: 0 | E70: 0 | F70: 0 | G70: 0 | H70: 0 | I70: 0 | J70: 0 | K70: 0 | L70: 0 | M70: 0 | N70: 0 | O70: 0 | P70: 0 | Q70: 0 | R70: 0 | S70: 0 | T70: 0
A71: G Suite | B71: BRL | C71: 0 | D71: 0 | E71: 0 | F71: 0 | G71: 0 | H71: 0 | I71: 0 | J71: 0 | K71: 0 | L71: 0 | M71: 0 | N71: 0 | O71: 0 | P71: 0 | Q71: 0 | R71: 0 | S71: 0 | T71: 0
A72: Adobe Creative Cloud | B72: BRL | C72: 0 | D72: 0 | E72: 0 | F72: 0 | G72: 0 | H72: 0 | I72: 0 | J72: 0 | K72: 0 | L72: 0 | M72: 0 | N72: 0 | O72: 0 | P72: 0 | Q72: 0 | R72: 0 | S72: 0 | T72: 0
A74: EBITDA | B74: BRL | C74: =C54-C57 | D74: =D54-D57 | E74: =E54-E57 | F74: =F54-F57 | G74: =G54-G57 | H74: =H54-H57 | I74: =I54-I57 | J74: =J54-J57 | ... T74: =T54-T57
A75: Operating Income (EBIT) | B75: BRL | C75: =C74 | D75: =D74 | E75: =E74 | F75: =F74 | G75: =G74 | H75: =H74 | I75: =I74 | J75: =J74 | ... T75: =T74
A76: EBITDA Margin | B76: % | C76: =IFERROR(C74/C24,0) | D76: =IFERROR(D74/D24,0) | E76: =IFERROR(E74/E24,0) | F76: =IFERROR(F74/F24,0) | G76: =IFERROR(G74/G24,0) | H76: =IFERROR(H74/H24,0) | I76: =IFERROR(I74/I24,0) | J76: =IFERROR(J74/J24,0) | ... T76: =IFERROR(T74/T24,0)

Sheet Inputs
A1: DADOS DE ENTRADA - BUSINESS PLAN UMATCH
A3: Seção | B3: Parâmetro | C3: Valor | D3: Unidade | E3: Observações
A4: Receita | B4: Taxa Apple/Google | C4: 0.85 | D4: % | E4: Receita líquida após desconto de 15%
A5: Receita | B5: Receita Bruta = Líquida / 0.85 | C5: =C4/C4 | D5: Fórmula | E5: Cálculo automático
A7: Custos | B7: COGS - AWS | D7: R$ | E7: Custo AWS (editável)
A8: Custos | B8: COGS - Cloudflare | D8: R$ | E8: Custo Cloudflare (editável)
A9: Custos | B9: COGS - Heroku | D9: R$ | E9: Custo Heroku (editável)
A10: Custos | B10: COGS - IAPHUB | D10: R$ | E10: Custo IAPHUB (editável)
A11: Custos | B11: COGS - MailGun | D11: R$ | E11: Custo MailGun (editável)
A12: Custos | B12: COGS - AWS SES | D12: R$ | E12: Custo AWS SES (editável)
A14: SG&A | B14: Marketing | D14: R$ | E14: Despesas de Marketing (editável)
A15: SG&A | B15: Wages | D15: R$ | E15: Salários e Pró-labore (editável)
A16: SG&A | B16: Tech Support & Services | D16: R$ | E16: Serviços de tecnologia (editável)
A18: Importação | B18: Status Importação | C18: Pendente | D18: Status | E18: Atualizado após importação
A19: Importação | B19: Última Atualização | D19: Data | E19: Data da última importação
A20: Importação | B20: Total Registros | D20: Qtd | E20: Quantidade de registros importados

Sheet Mapeamento
A1: MAPEAMENTO DE CENTROS DE CUSTO E FORNECEDORES
A3: Grupo Financeiro | B3: Centro de Custo (Conta Azul) | C3: Fornecedor/Cliente | D3: Linha P&L | E3: Tipo | F3: Ativo | G3: Observações
A4: Receita Google | B4: Google Play Net Revenue | C4: GOOGLE BRASIL PAGAMENTOS LTDA | D4: 25 | E4: Receita | F4: Sim | G4: Receita Google Play
A5: Receita Apple | B5: App Store Net Revenue | C5: App Store (Apple) | D5: 33 | E5: Receita | F5: Sim | G5: Receita App Store
A6: Receita Brasil | B6: Google Play Net Revenue | C6: GOOGLE BRASIL PAGAMENTOS LTDA | D6: 26 | E6: Receita | F6: Sim | G6: Receita Brasil - Google
A7: Receita Brasil | B7: App Store Net Revenue | C7: App Store (Apple) | D7: 34 | E7: Receita | F7: Sim | G7: Receita Brasil - Apple
A8: Receita USA | B8: Google Play Net Revenue | C8: GOOGLE BRASIL PAGAMENTOS LTDA | D8: 28 | E8: Receita | F8: Sim | G8: Receita USA - Google
A9: Receita USA | B9: App Store Net Revenue | C9: App Store (Apple) | D9: 36 | E9: Receita | F9: Sim | G9: Receita USA - Apple
A11: COGS | B11: Web Services Expenses | C11: AWS | D11: 43 | E11: Custo | F11: Sim | G11: Amazon Web Services
A12: COGS | B12: Web Services Expenses | C12: Cloudflare | D12: 44 | E12: Custo | F12: Sim | G12: Cloudflare
A13: COGS | B13: Web Services Expenses | C13: Heroku | D13: 45 | E13: Custo | F13: Sim | G13: Heroku
A14: COGS | B14: Web Services Expenses | C14: IAPHUB | D14: 46 | E14: Custo | F14: Sim | G14: IAPHUB
A15: COGS | B15: Web Services Expenses | C15: MailGun | D15: 47 | E15: Custo | F15: Sim | G15: MailGun
... A36: Rendimentos | B36: Rendimentos de Aplicações | C36: BANCO INTER | D36: 38 | E36: Receita | F36: Sim | G36: Rendimentos - Banco Inter

Sheet Extrato_Importado
A1: EXTRATO CONTA AZUL - DADOS IMPORTADOS
A3: Data Competência | B3: Centro de Custo | C3: Fornecedor/Cliente | D3: Descrição | E3: Valor (R$) | F3: Tipo Operação | G3: Categoria | H3: Mês | I3: Grupo Mapeado | J3: Linha P&L
A4: 45901 | B4: Other Taxes | C4: BANCO INTER | D4: Ajuste de cota/precificação para alinhar ao extrato (valor bruto) | E4: 438.62 | F4: Crédito | G4: Ajuste de cotas | H4: 2025-09
A5: 45901 | B5: Marketing & Growth Expenses | D5: Jonatthan Marllon Espinola Reganham - Transferência | Pix | E5: -74 | F5: Débito | G5: Marketing e Publicidade - Sem NF | H5: 2025-09
A6: 45901 | B6: Rendimentos de Aplicações | C6: CONTA SIMPLES | D6: Rentabilidade CDI - Remuneração-Cta Pgto | E6: 5.7 | F6: Crédito | G6: Rendimentos de Aplicações | H6: 2025-09
A7: 45902 | B7: Rendimentos de Aplicações | C7: CONTA SIMPLES | D7: Rentabilidade CDI - Remuneração-Cta Pgto | E7: 23.9 | F7: Crédito | G7: Rendimentos de Aplicações | H7: 2025-09
A8: 45903 | B8: Rendimentos de Aplicações | C8: CONTA SIMPLES | D8: Rentabilidade CDI - Remuneração-Cta Pgto | E8: 23.4 | F8: Crédito | G8: Rendimentos de Aplicações | H8: 2025-09
A9: 45904 | B9: Rendimentos de Aplicações | C9: CONTA SIMPLES | D9: Rentabilidade CDI - Remuneração-Cta Pgto | E9: 24.83 | F9: Crédito | G9: Rendimentos de Aplicações | H9: 2025-09
A10: 45905 | D10: Pix enviado - Umatch Ltda | E10: 47610 | F10: Crédito | G10: Transferência de Entrada | H10: 2025-09
A11: 45905 | D11: Pix enviado - Umatch Ltda | E11: -47610 | F11: Débito | G11: Transferência de Saída | H11: 2025-09
A12: 45905 | B12: Marketing & Growth Expenses | D12: Higor Natan Costa Barbosa - Transferência | Pix | E12: -2564 | F12: Débito | G12: Marketing e Publicidade - Sem NF | H12: 2025-09
A13: 45905 | B13: Marketing & Growth Expenses | D13: GUSTAVO CRUZ SILVA - Transferência | Pix | E13: -1854 | F13: Débito | G13: Marketing e Publicidade - Sem NF | H13: 2025-09
A14: 45905 | B14: Marketing & Growth Expenses | D14: Alan Pereira dos Anjos - Transferência | Pix | E14: -1786 | F14: Débito | G14: Marketing e Publicidade - Sem NF | H14: 2025-09
A15: 45905 | B15: Marketing & Growth Expenses | D15: Rian da Silva Mascarenhas - Transferência | Pix | E15: -1602 | F15: Débito | G15: Marketing e Publicidade - Sem NF | H15: 2025-09
A16: 45905 | B16: Marketing & Growth Expenses | D16: Nataniele Cristian Nonato dos Anjos - Transferência | Pix | E16: -1372 | F16: Débito | G16: Marketing e Publicidade - Sem NF | H16: 2025-09
A17: 45905 | B17: Marketing & Growth Expenses | D17: Arthur de Queiros Alves - Transferência | Pix | E17: -1260 | F17: Débito | G17: Marketing e Publicidade - Sem NF | H17: 2025-09
A18: 45905 | B18: Marketing & Growth Expenses | D18: Dalva Alves Costa - Transferência | Pix | E18: -1240 | F18: Débito | G18: Marketing e Publicidade - Sem NF | H18: 2025-09
A19: 45905 | B19: Marketing & Growth Expenses | D19: Gabriel Santos de Freitas - Transferência | Pix | E19: -1178 | F19: Débito | G19: Marketing e Publicidade - Sem NF | H19: 2025-09
A20: 45905 | B20: Marketing & Growth Expenses | D20: Evellyn Alves Melo - Transferência | Pix | E20: -1096 | F20: Débito | G20: Marketing e Publicidade - Sem NF | H20: 2025-09
A21: 45905 | B21: Marketing & Growth Expenses | D21: Rafael Pimenta Vieira - Transferência | Pix | E21: -882 | F21: Débito | G21: Marketing e Publicidade - Sem NF | H21: 2025-09
A22: 45905 | B22: Marketing & Growth Expenses | D22: Nathalia Cristina Lucas Elias - Transferência | Pix | E22: -876 | F22: Débito | G22: Marketing e Publicidade - Sem NF | H22: 2025-09
A23: 45905 | B23: Marketing & Growth Expenses | D23: VALDIR PELIK CALAZANS - Transferência | Pix | E23: -1090 | F23: Débito | G23: Marketing e Publicidade - Sem NF | H23: 2025-09
... A101: 45905 | B101: Marketing & Growth Expenses | D101: Victoria Fonseca Moreira Silva - Transferência | Pix | E101: -2 | F101: Débito | G101: Marketing e Publicidade - Sem NF | H101: 2025-09
A102: 45905 | B102: Rendimentos de Aplicações | C102: CONTA SIMPLES | D102: Rentabilidade CDI | E102: 29.12 | F102: Crédito | G102: Rendimentos de Aplicações | H102: 2025-09
A103: 45906 | B103: Rendimentos de Aplicações | C103: CONTA SIMPLES | D103: Rentabilidade CDI - Remuneração-Cta Pgto | E103: 27.93 | F103: Crédito | G103: Rendimentos de Aplicações | H103: 2025-09
A104: 45907 | B104: Rendimentos de Aplicações | C104: CONTA SIMPLES | D104: Rentabilidade CDI - Remuneração-Cta Pgto | E104: 9.26 | F104: Crédito | G104: Rendimentos de Aplicações | H104: 2025-09
A105: 45908 | B105: Rendimentos de Aplicações | C105: CONTA SIMPLES | D105: Rentabilidade CDI | E105: 12.34 | F105: Crédito | G105: Rendimentos de Aplicações | H105: 2025-09
A106: 45908 | B106: Identificar | D106: PIX Enviado para KANAYAMA SUSHI LTDA | E106: -901.85 | F106: Débito | G106: Despesas a identificar | H106: 2025-09
A107: 45909 | B107: Rendimentos de Aplicações | C107: CONTA SIMPLES | D107: Rentabilidade CDI - Remuneração-Cta Pgto | E107: 30.73 | F107: Crédito | G107: Rendimentos de Aplicações | H107: 2025-09
A108: 45889 | B108: Travel | C108: American Airlines | D108: AMERICAN AIR* captureRe | E108: -12194.91 | F108: Débito | G108: Viagens e Representações | H108: 2025-08
A109: 45887 | B109: Tech Support & Services | C109: Adobe | D109: ADOBE | E109: -139 | F109: Débito | G109: Software / Licença de Uso | H109: 2025-08
A110: 45894 | B110: Tech Support & Services | C110: Adobe | D110: ADOBE | E110: -139 | F110: Débito | G110: Software / Licença de Uso | H110: 2025-08
A111: 45874 | B111: Tech Support & Services | C111: COMPANYHERO SAO PAULO BRA | D111: COMPANY HERO | E111: -136 | F111: Débito | G111: Software / Licença de Uso | H111: 2025-08
A112: 45881 | B112: Tech Support & Services | C112: ClickSign | D112: CLICK SIGN*Clicksign | E112: -39 | F112: Débito | G112: Software / Licença de Uso | H112: 2025-08
A113: 45899 | B113: Tech Support & Services | C113: Canva | D113: EBN*CANVA0462 | E113: -35 | F113: Débito | G113: Software / Licença de Uso | H113: 2025-08
A114: 45910 | D114: Origem: Conta Corrente - Banco Inter / Destino: Conta Corrente - Banco Stone | E114: 15170 | F114: Crédito | G114: Transferência de Entrada | H114: 2025-09
A115: 45910 | D115: Origem: Conta Corrente - Banco Inter / Destino: Conta Corrente - Banco Stone | E115: -15170 | F115: Débito | G115: Transferência de Saída | H115: 2025-09
A116: 45870 | B116: Payroll Tax - Brazil | C116: IMPOSTOS/TRIBUTOS | D116: DAMSP - DARF ISS 08.2025 | E116: -17 | F116: Débito | G116: Retenção - ISS Serviços Tomados | H116: 2025-08
A117: 45870 | B117: Legal & Accounting Expenses | C117: BHUB.AI | D117: NF 34182 - BHUB - MENSALIDADE BPO FINANCEIRO | E117: -3294.14 | F117: Débito | G117: Honorários BPO Financeiro | H117: 2025-08
A118: 45870 | B118: Legal & Accounting Expenses | C118: BHUB.AI | D118: NF 34182 - BHUB - MENSALIDADE CONTÁBIL | E118: -1251.77 | F118: Débito | G118: Honorários Contábeis | H118: 2025-08
A119: 45910 | B119: Marketing & Growth Expenses | D119: Alef Rodrigues dos Santos Borges - Transferência | Pix | E119: -210 | F119: Débito | G119: Marketing e Publicidade - Sem NF | H119: 2025-09
A120: 45910 | B120: Marketing & Growth Expenses | D120: ANTONIA ROSYANNY SOARES CAVALCANTE - Transferência | Pix | E120: -88 | F120: Débito | G120: Marketing e Publicidade - Sem NF | H120: 2025-09
A121: 45910 | B121: Marketing & Growth Expenses | D121: Aline lopes da silva - Transferência | Pix | E121: -196 | F121: Débito | G121: Marketing e Publicidade - Sem NF | H121: 2025-09
A122: 45910 | B122: Marketing & Growth Expenses | D122: ANA PAULA SILVA MAGGI - Transferência | Pix | E122: -68 | F122: Débito | G122: Marketing e Publicidade - Sem NF | H122: 2025-09
A123: 45910 | B123: Marketing & Growth Expenses | D123: Alice Magalhaes Sampaio - Transferência | Pix | E123: -30 | F123: Débito | G123: Marketing e Publicidade - Sem NF | H123: 2025-09
A124: 45910 | B124: Marketing & Growth Expenses | D124: Amanda Lima Dos Santos - Transferência | Pix | E124: -64 | F124: Débito | G124: Marketing e Publicidade - Sem NF | H124: 2025-09
A125: 45910 | B125: Marketing & Growth Expenses | D125: ANDERSON DOS SANTOS SILVA - Transferência | Pix | E125: -4 | F125: Débito | G125: Marketing e Publicidade - Sem NF | H125: 2025-09
A126: 45910 | B126: Marketing & Growth Expenses | D126: ANA CLARA NASCIMENTO DA SILVA - Transferência | Pix | E126: -2 | F126: Débito | G126: Marketing e Publicidade - Sem NF | H126: 2025-09
A127: 45910 | B127: Marketing & Growth Expenses | D127: Ana Julia Araujo Menezes - Transferência | Pix | E127: -12 | F127: Débito | G127: Marketing e Publicidade - Sem NF | H127: 2025-09
A128: 45910 | B128: Marketing & Growth Expenses | D128: Ana Karolina Pinto Cruz Mascarenhas - Transferência | Pix | E128: -2 | F128: Débito | G128: Marketing e Publicidade - Sem NF | H128: 2025-09
A129: 45910 | B129: Marketing & Growth Expenses | D129: Andre Henrique Baggio - Transferência | Pix | E129: -4 | F129: Débito | G129: Marketing e Publicidade - Sem NF | H129: 2025-09
A130: 45910 | B130: Marketing & Growth Expenses | D130: Beatriz Cubateli Bogo - Transferência | Pix | E130: -34 | F130: Débito | G130: Marketing e Publicidade - Sem NF | H130: 2025-09
... A256: 45910 | B256: Marketing & Growth Expenses | D256: VINICIO PIRES MARTINS - Transferência | Pix | E256: -2 | F256: Débito | G256: Marketing e Publicidade - Sem NF | H256: 2025-09
A257: 45910 | B257: Rendimentos de Aplicações | C257: CONTA SIMPLES | D257: Rentabilidade CDI | E257: 32.15 | F257: Crédito | G257: Rendimentos de Aplicações | H257: 2025-09
A258: 45910 | B258: Identificar | D258: PIX Enviado para EBANX Ltda. | E258: -269 | F258: Débito | G258: Despesas a identificar | H258: 2025-09
A259: 45911 | B259: Rendimentos de Aplicações | C259: CONTA SIMPLES | D259: Rentabilidade CDI - Remuneração-Cta Pgto | E259: 37.18 | F259: Crédito | G259: Rendimentos de Aplicações | H259: 2025-09
A260: 45912 | B260: Rendimentos de Aplicações | C260: CONTA SIMPLES | D260: Rentabilidade CDI | E260: 35.1 | F260: Crédito | G260: Rendimentos de Aplicações | H260: 2025-09
A261: 45912 | B261: Identificar | D261: PIX Enviado para MARELOI COMERCIAL LTDA | E261: -130.75 | F261: Débito | G261: Despesas a identificar | H261: 2025-09
A262: 45881 | B262: Tech Support & Services | D262: 1PASSWORD | E262: -619.48 | F262: Débito | G262: Software / Licença de Uso | H262: 2025-08
A263: 45881 | B263: Other Taxes | D263: 1PASSWORD | E263: -21.68 | F263: Débito | G263: IOF | H263: 2025-08
A264: 45905 | B264: Other Taxes | D264: 650 INDUSTRIES (EXPO) | E264: -9.49 | F264: Débito | G264: IOF | H264: 2025-09
A265: 45905 | B265: Tech Support & Services | D265: 650 INDUSTRIES (EXPO) | E265: -271.16 | F265: Débito | G265: Software / Licença de Uso | H265: 2025-09
A266: 45907 | B266: Other Taxes | D266: AGORAPULSE SAS | E266: -9.69 | F266: Débito | G266: IOF | H266: 2025-09
A267: 45907 | B267: Tech Support & Services | D267: AGORAPULSE SAS | E267: -276.81 | F267: Débito | G267: Software / Licença de Uso | H267: 2025-09
A268: 45881 | B268: Tech Support & Services | D268: AMPLITUDE, INC. | E268: -17757.49 | F268: Débito | G268: Software / Licença de Uso | H268: 2025-08
A269: 45881 | B269: Other Taxes | D269: AMPLITUDE, INC. | E269: -621.51 | F269: Débito | G269: IOF | H269: 2025-08
A270: 45901 | B270: Tech Support & Services | D270: APPLE.COM/BILL | E270: -109 | F270: Débito | G270: Software / Licença de Uso | H270: 2025-09
A271: 45903 | B271: Tech Support & Services | D271: ASAAS*SOCIALHUB SERVICOS | E271: -199 | F271: Débito | G271: Software / Licença de Uso | H271: 2025-09
A272: 45901 | B272: Web Services Expenses | D272: AWS BRAZIL | E272: -241.06 | F272: Débito | G272: Software / Licença de Uso | H272: 2025-09
... A363: 45890 | B363: web Services Expenses | D363: HOTEL AT BOOKING.COM | E363: -3795.62 | F363: Débito | G363: Software / Licença de Uso | H363: 2025-08
A364: 45913 | B364: Rendimentos de Aplicações | C364: CONTA SIMPLES | D364: Rentabilidade CDI - Remuneração-Cta Pgto | E364: 36.44 | F364: Crédito | G364: Rendimentos de Aplicações | H364: 2025-09
A365: 45914 | B365: Rendimentos de Aplicações | C365: CONTA SIMPLES | D365: Rentabilidade CDI - Remuneração-Cta Pgto | E365: 16.79 | F365: Crédito | G365: Rendimentos de Aplicações | H365: 2025-09
A366: 45915 | D366: Transferência de limite - Deposito de limite 2025-09-15T11:37:21.134Z | E366: 38014.04 | F366: Crédito | G366: Transferência de Entrada | H366: 2025-09
A367: 45870 | B367: Wages Expenses | C367: VITORIA DE OLIVEIRA FERREIRA CORREA | D367: NF 06 - SERVIÇOS PRESTADOS | E367: -12000 | F367: Débito | G367: Prestador de Serviço PJ (Com NF) | H367: 2025-08
A368: 45870 | B368: Wages Expenses | C368: JONAS JERONIMO CHAVES DE SOUSA | D368: NF 12 - SERVIÇOS PRESTADOS - TÉRMINO DO CONTRATO | E368: -7741.94 | F368: Débito | G368: Prestador de Serviço PJ (Com NF) | H368: 2025-08
A369: 45870 | B369: Wages Expenses | C369: BEATRIZ MATHIDIOS DE OLIVEIRA | D369: NF 08 - SERVIÇOS PRESTADOS | E369: -4500 | F369: Débito | G369: Prestador de Serviço PJ (Com NF) | H369: 2025-08
A370: 45870 | B370: Wages Expenses | C370: MARCO ANTONIO PEREIRA DO ESPIRITO SANTO | D370: NF 23 - SERVIÇOS PRESTADOS | E370: -3792 | F370: Débito | G370: Prestador de Serviço PJ (Com NF) | H370: 2025-08
A371: 45870 | B371: Wages Expenses | C371: MANASSES QUEIROZ SILVA | D371: NF 07 - SERVIÇOS PRESTADOS | E371: -3473.67 | F371: Débito | G371: Prestador de Serviço PJ (Com NF) | H371: 2025-08
A372: 45870 | B372: Wages Expenses | C372: NUVATE (FILIPI RAFAEL) | D372: NF 14 - SERVIÇOS PRESTADOS | E372: -9000 | F372: Débito | G372: Prestador de Serviço PJ (Com NF) | H372: 2025-08
A373: 45870 | B373: Wages Expenses | C373: GABRIEL CANTARIN SIMOES | D373: NF 02 - SERVIÇOS PRESTADOS | E373: -20000 | F373: Débito | G373: Prestador de Serviço PJ (Com NF) | H373: 2025-08
A374: 45870 | B374: Wages Expenses | C374: PEDRO GERMANO | D374: NFS 00000016 - Serviços Administrativos - 08/2025 | E374: -5785.71 | F374: Débito | G374: Prestador de Serviço PJ (Com NF) | H374: 2025-08
A375: 45870 | B375: Wages Expenses | C375: Bruno Adami Serine | D375: ANTECIPAÇÃO DE LUCROS | E375: -13743.32 | F375: Débito | G375: Antecipação de Lucros | H375: 2025-08
A376: 45870 | B376: Wages Expenses | C376: Bruno Adami Serine | D376: PRÓ LABORE | E376: -1256.68 | F376: Débito | G376: Pró-labore | H376: 2025-08
A377: 45870 | B377: Other Expenses | C377: VITORIA DE OLIVEIRA FERREIRA CORREA | D377: Reembolso Despesas EUA | E377: -4656.23 | F377: Débito | G377: Reembolsos Colaboradores | H377: 2025-08
A378: 45870 | B378: Other Expenses | C378: GABRIEL CANTARIN SIMOES | D378: Comprovante GRU Judicial - 08/2025 | E378: -438 | F378: Débito | G378: Reembolso | H378: 2025-08
A379: 45915 | B379: Rendimentos de Aplicações | C379: CONTA SIMPLES | D379: Rentabilidade CDI | E379: 12.58 | F379: Crédito | G379: Rendimentos de Aplicações | H379: 2025-09
A380: 45915 | D380: Transferência de limite - Deposito de limite 2025-09-15T11:37:21.134Z | E380: -38014.04 | F380: Débito | G380: Transferência de Saída | H380: 2025-09
A381: 45870 | B381: Marketing & Growth Expenses | C381: MGA MARKETING LTDA | D381: NFS 00004508 - Serviço de Marketing Direto - ago/2025 | E381: -8500 | F381: Débito | G381: Marketing e Publicidade | H381: 2025-08
A382: 45919 | B382: Google Play Net Revenue | C382: GOOGLE BRASIL PAGAMENTOS LTDA | D382: Venda 7 / NFS-e:63 - RPS:65 | E382: 136705.49 | F382: Crédito | G382: Receitas de Vendas | H382: 2025-09
A383: 45916 | B383: Rendimentos de Aplicações | C383: CONTA SIMPLES | D383: Rentabilidade CDI - Remuneração-Cta Pgto | E383: 18.44 | F383: Crédito | G383: Rendimentos de Aplicações | H383: 2025-09
A384: 45919 | B384: App Store Net Revenue | C384: App Store (Apple) | D384: Venda 8 / NFS-e:64 - RPS:66 | E384: 229710.01 | F384: Crédito | G384: Receitas de Vendas | H384: 2025-09
A385: 45917 | B385: Rendimentos de Aplicações | C385: CONTA SIMPLES | D385: Rentabilidade CDI - Remuneração-Cta Pgto | E385: 20.73 | F385: Crédito | G385: Rendimentos de Aplicações | H385: 2025-09
A386: 45918 | B386: Rendimentos de Aplicações | C386: CONTA SIMPLES | D386: Rentabilidade CDI - Remuneração-Cta Pgto | E386: 19.57 | F386: Crédito | G386: Rendimentos de Aplicações | H386: 2025-09
A387: 45870 | B387: Office Expenses | C387: GO OFFICES LATAM S/A | D387: REF. ALUGUEL MENSAL | E387: -7650 | F387: Débito | G387: Aluguel | H387: 2025-08
A388: 45870 | B388: Legal & Accounting Expenses | C388: WOLFF E SCRIPES ADVOGADOS | D388: NF 1611 - HONORÁRIOS ADVOCATÍCIOS | E388: -1295.57 | F388: Débito | G388: Honorários Advocatícios | H388: 2025-08
A389: 45870 | B389: Legal & Accounting Expenses | C389: WOLFF E SCRIPES ADVOGADOS | D389: Reembolso de Despesas - Cópia de Inquérito Policial - ago/2025 | E389: -52.62 | F389: Débito | G389: Honorários Advocatícios | H389: 2025-08
A390: 45870 | B390: Office Expenses | C390: CO-SERVICES DO BRASIL SERVICOS COMBINADOS DE APOIO A EDIFICIOS LTDA | D390: NF 23051 - REF. SERVIÇOS DE FACILITES | E390: -739.5 | F390: Débito | G390: Aluguel | H390: 2025-08
A391: 45870 | B391: Payroll Tax - Brazil | C391: IMPOSTOS/TRIBUTOS | D391: RECEITA FEDERAL/SP - DARF INSS | E391: -166.98 | F391: Débito | G391: INSS sobre Pró-labore - GPS | H391: 2025-08
A392: 45870 | B392: Payroll Tax - Brazil | C392: IMPOSTOS/TRIBUTOS | D392: RECEITA FEDERAL/SP - DARF INSS | E392: -93.5 | F392: Débito | G392: Retenção - GPS 2631 - INSS | H392: 2025-08
A393: 45919 | B393: Marketing & Growth Expenses | D393: Alexsandra Vitoria Bento Da Silva - Transferência | Pix | E393: -22 | F393: Débito | G393: Marketing e Publicidade - Sem NF | H393: 2025-09
...

Sheet DRE
A1: DEMONSTRAÇÃO DO RESULTADO DO EXERCÍCIO (DRE)
A3: Linha DRE | B3: Unidade | C3: 05/2024 | D3: 06/2024 | E3: 07/2024 | F3: 08/2024 | G3: 09/2024 | H3: 10/2024 | I3: 11/2024 | J3: 12/2024 | K3: 01/2025 | L3: 02/2025 | M3: 03/2025 | N3: 04/2025 | O3: 05/2025 | P3: 06/2025 | Q3: 07/2025 | R3: 08/2025 | S3: 09/2025 | T3: 10/2025
A5: RECEITA OPERACIONAL BRUTA | B5: BRL | C5: ='P&L'!C24 | D5: ='P&L'!D24 | E5: ='P&L'!E24 | F5: ='P&L'!F24 | G5: ='P&L'!G24 | H5: ='P&L'!H24 | I5: ='P&L'!I24 | J5: ='P&L'!J24 | ... T5: ='P&L'!T24
A6: Receita de Vendas (Google + Apple) | B6: BRL | C6: ='P&L'!C25 | D6: ='P&L'!D25 | E6: ='P&L'!E25 | F6: ='P&L'!F25 | G6: ='P&L'!G25 | H6: ='P&L'!H25 | I6: ='P&L'!I25 | J6: ='P&L'!J25 | ... T6: ='P&L'!T25
A7: Rendimentos de Aplicações | B7: BRL | C7: ='P&L'!C42 | D7: ='P&L'!D42 | E7: ='P&L'!E42 | F7: ='P&L'!F42 | G7: ='P&L'!G42 | H7: ='P&L'!H42 | I7: ='P&L'!I42 | J7: ='P&L'!J42 | ... T7: ='P&L'!T42
A9: (-) CUSTOS DIRETOS | B9: BRL | C9: ='P&L'!C44 | D9: ='P&L'!D44 | E9: ='P&L'!E44 | F9: ='P&L'!F44 | G9: ='P&L'!G44 | H9: ='P&L'!H44 | I9: ='P&L'!I44 | J9: ='P&L'!J44 | ... T9: ='P&L'!T44
A10: Payment Processing | B10: BRL | C10: ='P&L'!C45 | D10: ='P&L'!D45 | E10: ='P&L'!E45 | F10: ='P&L'!F45 | G10: ='P&L'!G45 | H10: ='P&L'!H45 | I10: ='P&L'!I45 | J10: ='P&L'!J45 | ... T10: ='P&L'!T45
A11: COGS (Custo dos Produtos Vendidos) | B11: BRL | C11: ='P&L'!C46 | D11: ='P&L'!D46 | E11: ='P&L'!E46 | F11: ='P&L'!F46 | G11: ='P&L'!G46 | H11: ='P&L'!H46 | I11: ='P&L'!I46 | J11: ='P&L'!J46 | ... T11: ='P&L'!T46
A13: (=) LUCRO BRUTO | B13: BRL | C13: ='P&L'!C54 | D13: ='P&L'!D54 | E13: ='P&L'!E54 | F13: ='P&L'!F54 | G13: ='P&L'!G54 | H13: ='P&L'!H54 | I13: ='P&L'!I54 | J13: ='P&L'!J54 | ... T13: ='P&L'!T54
A14: Margem Bruta (%) | B14: % | C14: ='P&L'!C55 | D14: ='P&L'!D55 | E14: ='P&L'!E55 | F14: ='P&L'!F55 | G14: ='P&L'!G55 | H14: ='P&L'!H55 | I14: ='P&L'!I55 | J14: ='P&L'!J55 | ... T14: ='P&L'!T55
A16: (-) DESPESAS OPERACIONAIS | B16: BRL | C16: ='P&L'!C57 | D16: ='P&L'!D57 | E16: ='P&L'!E57 | F16: ='P&L'!F57 | G16: ='P&L'!G57 | H16: ='P&L'!H57 | I16: ='P&L'!I57 | J16: ='P&L'!J57 | ... T16: ='P&L'!T57
A17: R&D | B17: BRL | C17: ='P&L'!C58 | D17: ='P&L'!D58 | E17: ='P&L'!E58 | F17: ='P&L'!F58 | G17: ='P&L'!G58 | H17: ='P&L'!H58 | I17: ='P&L'!I58 | J17: ='P&L'!J58 | ... T17: ='P&L'!T58
A18: SG&A | B18: BRL | C18: ='P&L'!C59 | D18: ='P&L'!D59 | E18: ='P&L'!E59 | F18: ='P&L'!F59 | G18: ='P&L'!G59 | H18: ='P&L'!H59 | I18: ='P&L'!I59 | J18: ='P&L'!J59 | ... T18: ='P&L'!T59
A19: Marketing | B19: BRL | C19: ='P&L'!C60 | D19: ='P&L'!D60 | E19: ='P&L'!E60 | F19: ='P&L'!F60 | G19: ='P&L'!G60 | H19: ='P&L'!H60 | I19: ='P&L'!I60 | J19: ='P&L'!J60 | ... T19: ='P&L'!T60
A20: Salários (Wages) | B20: BRL | C20: ='P&L'!C68 | D20: ='P&L'!D68 | E20: ='P&L'!E68 | F20: ='P&L'!F68 | G20: ='P&L'!G68 | H20: ='P&L'!H68 | I20: ='P&L'!I68 | J20: ='P&L'!J68 | ... T20: ='P&L'!T68
A21: Tech Support & Services | B21: BRL | C21: ='P&L'!C69 | D21: ='P&L'!D69 | E21: ='P&L'!E69 | F21: ='P&L'!F69 | G21: ='P&L'!G69 | H21: ='P&L'!H69 | I21: ='P&L'!I69 | J21: ='P&L'!J69 | ... T21: ='P&L'!T69
A23: (=) EBITDA | B23: BRL | C23: ='P&L'!C74 | D23: ='P&L'!D74 | E23: ='P&L'!E74 | F23: ='P&L'!F74 | G23: ='P&L'!G74 | H23: ='P&L'!H74 | I23: ='P&L'!I74 | J23: ='P&L'!J74 | ... T23: ='P&L'!T74
A24: Margem EBITDA (%) | B24: % | C24: ='P&L'!C76 | D24: ='P&L'!D76 | E24: ='P&L'!E76 | F24: ='P&L'!F76 | G24: ='P&L'!G76 | H24: ='P&L'!H76 | I24: ='P&L'!I76 | J24: ='P&L'!J76 | ... T24: ='P&L'!T76
A26: (=) RESULTADO OPERACIONAL (EBIT) | B26: BRL | C26: ='P&L'!C75 | D26: ='P&L'!D75 | E26: ='P&L'!E75 | F26: ='P&L'!F75 | G26: ='P&L'!G75 | H26: ='P&L'!H75 | I26: ='P&L'!I75 | J26: ='P&L'!J75 | ... T26: ='P&L'!T75
A28: INDICADORES-CHAVE
A29: NAU (Net Active Users) | B29: % | C29: ='P&L'!C5 | D29: ='P&L'!D5 | E29: ='P&L'!E5 | F29: ='P&L'!F5 | G29: ='P&L'!G5 | H29: ='P&L'!H5 | I29: ='P&L'!I5 | J29: ='P&L'!J5 | ... T29: ='P&L'!T5
A30: CPA (Cost Per Acquisition) | B30: % | C30: ='P&L'!C16 | D30: ='P&L'!D16 | E30: ='P&L'!E16 | F30: ='P&L'!F16 | G30: ='P&L'!G16 | H30: ='P&L'!H16 | I30: ='P&L'!I16 | J30: ='P&L'!J16 | ... T30: ='P&L'!T16
A31: Marketing / Revenue no Tax (%) | B31: % | C31: ='P&L'!C61 | D31: ='P&L'!D61 | E31: ='P&L'!E61 | F31: ='P&L'!F61 | G31: ='P&L'!G61 | H31: ='P&L'!H61 | I31: ='P&L'!I61 | J31: ='P&L'!J61 | ... T31: ='P&L'!T61

Sheet Dashboard
A1: DASHBOARD - INDICADORES E ANÁLISES
A3: KPIS PRINCIPAIS (Último Mês Disponível)
A5: Receita Total | B5: ='P&L'!T24
A6: EBITDA | B6: ='P&L'!T74
A7: Margem EBITDA | B7: ='P&L'!T76
A8: Gross Margin | B8: ='P&L'!T55
A9: NAU | B9: ='P&L'!T5
A10: CPA | B10: ='P&L'!T16
A13: RESUMO MENSAL (Últimos 6 Meses)
A15: Mês | B15: Receita | C15: COGS | D15: Gross Profit | E15: OpEx | F15: EBITDA | G15: Margem EBITDA
A16: ='P&L'!O3 | B16: ='P&L'!O24 | C16: ='P&L'!O44 | D16: ='P&L'!O54 | E16: ='P&L'!O57 | F16: ='P&L'!O74 | G16: ='P&L'!O76
A17: ='P&L'!P3 | B17: ='P&L'!P24 | C17: ='P&L'!P44 | D17: ='P&L'!P54 | E17: ='P&L'!P57 | F17: ='P&L'!P74 | G17: ='P&L'!P76
A18: ='P&L'!Q3 | B18: ='P&L'!Q24 | C18: ='P&L'!Q44 | D18: ='P&L'!Q54 | E18: ='P&L'!Q57 | F18: ='P&L'!Q74 | G18: ='P&L'!Q76
A19: ='P&L'!R3 | B19: ='P&L'!R24 | C19: ='P&L'!R44 | D19: ='P&L'!R54 | E19: ='P&L'!R57 | F19: ='P&L'!R74 | G19: ='P&L'!R76
A20: ='P&L'!S3 | B20: ='P&L'!S24 | C20: ='P&L'!S44 | D20: ='P&L'!S54 | E20: ='P&L'!S57 | F20: ='P&L'!S74 | G20: ='P&L'!S76
A21: ='P&L'!T3 | B21: ='P&L'!T24 | C21: ='P&L'!T44 | D21: ='P&L'!T54 | E21: ='P&L'!T57 | F21: ='P&L'!T74 | G21: ='P&L'!T76
A24: ANÁLISE DE CUSTOS (Último Mês)
A26: Payment Processing | B26: ='P&L'!T45 | C26: =='P&L'!T45/('P&L'!T24) | D26: % da Receita
A27: COGS Total | B27: ='P&L'!T46 | C27: =='P&L'!T46/('P&L'!T24) | D27: % da Receita
A28: Marketing | B28: ='P&L'!T60 | C28: =='P&L'!T60/('P&L'!T24) | D28: % da Receita
A29: Wages | B29: ='P&L'!T68 | C29: =='P&L'!T68/('P&L'!T24) | D29: % da Receita
A30: Tech Support | B30: ='P&L'!T69 | C30: =='P&L'!T69/('P&L'!T24) | D30: % da Receita

Sheet Glossário
A1: GLOSSÁRIO DE TERMOS E SIGLAS
A3: Termo/Sigla | B3: Nome Completo | C3: Definição
A4: NAU | B4: Net Active Users | C4: Número de usuários ativos líquidos no período
A5: MAU | B5: Monthly Active Users | C5: Número de usuários ativos mensais
A6: CPA | B6: Cost Per Acquisition | C6: Custo de aquisição por usuário (Marketing / NAU)
A7: ARPU | B7: Average Revenue Per User | C7: Receita média por usuário
A8: ARPPU | B8: Average Revenue Per Paying User | C8: Receita média por usuário pagante
A9: COGS | B9: Cost of Goods Sold | C9: Custo dos Produtos Vendidos (CMV) - custos diretos de infraestrutura
A10: SG&A | B10: Selling, General & Administrative | C10: Despesas de Vendas, Gerais e Administrativas
A11: EBITDA | B11: Earnings Before Interest, Taxes, Depreciation and Amortization | C11: Lucro antes de Juros, Impostos, Depreciação e Amortização
A12: EBIT | B12: Earnings Before Interest and Taxes | C12: Lucro antes de Juros e Impostos (Resultado Operacional)
A13: OpEx | B13: Operating Expenses | C13: Despesas Operacionais (R&D + SG&A)
A14: R&D | B14: Research & Development | C14: Pesquisa e Desenvolvimento
... A22: IAPHUB | B22: In-App Purchase Hub | C22: Plataforma de gerenciamento de compras in-app

Sheet Checklist
A1: CHECKLIST DE IMPLANTAÇÃO E USO
A3: Etapa | B3: Descrição | C3: Status | D3: Observações
A4: 1. Importação | B4: Importar extrato do Conta Azul (CSV) | C4: ✓ | D4: Dados já importados na aba Extrato_Importado
A5: 2. Mapeamento | B5: Revisar e ajustar mapeamento de centros de custo | C5: ⚠ | D5: Verificar aba Mapeamento e adicionar novos fornecedores se necessário
A6: 3. Parâmetros | B6: Configurar parâmetros editáveis | C6: ⚠ | D6: Preencher campos amarelos na aba Inputs
A7: 4. Validação P&L | B7: Validar cálculos automáticos do P&L | C7: ⚠ | D7: Verificar se valores importados estão corretos
A8: 5. Validação DRE | B8: Validar DRE consolidado | C8: ⚠ | D8: Conferir totalizações e margens
A9: 6. Dashboard | B9: Analisar KPIs e indicadores | C9: ⚠ | D9: Revisar gráficos e métricas principais
A10: 7. Documentação | B10: Documentar premissas e ajustes | C10: ⚠ | D10: Registrar observações na aba Inputs
A11: 8. Backup | B11: Salvar cópia de segurança | C11: ⚠ | D11: Manter versões anteriores para auditoria
A14: INSTRUÇÕES DE USO:
A15: 1. Exportar extrato do Conta Azul em formato CSV
A16: 2. Substituir dados na aba Extrato_Importado (copiar e colar)
A17: 3. Verificar se novos fornecedores/clientes precisam ser mapeados na aba Mapeamento
A18: 4. Preencher campos editáveis (amarelos) na aba Inputs conforme necessário
A19: 5. As fórmulas do P&L e DRE são atualizadas automaticamente
A20: 6. Revisar Dashboard para análise de tendências e KPIs
A21: 7. Campos não importados podem ser preenchidos manualmente no P&L
